{"Classes":[{"Members":[{"Category":"Data","MemberType":"Property","Name":"CollisionEnabled","Security":{"Read":"None","Write":"None"},"Serialization":{"CanLoad":false,"CanSave":false},"Tags":["ReadOnly","NotReplicated"],"ThreadSafety":"ReadSafe","ValueType":{"Category":"Primitive","Name":"bool"}},{"Category":"Data","MemberType":"Property","Name":"GridSize","Security":{"Read":"None","Write":"None"},"Serialization":{"CanLoad":false,"CanSave":false},"Tags":["ReadOnly","NotReplicated"],"ThreadSafety":"ReadSafe","ValueType":{"Category":"Primitive","Name":"float"}},{"Category":"Data","MemberType":"Property","Name":"HostDataModelType","Security":{"Read":"RobloxScriptSecurity","Write":"RobloxScriptSecurity"},"Serialization":{"CanLoad":false,"CanSave":false},"Tags":["Hidden","ReadOnly","NotReplicated"],"ThreadSafety":"ReadSafe","ValueType":{"Category":"Enum","Name":"StudioDataModelType"}},{"Category":"Data","MemberType":"Property","Name":"HostDataModelTypeIsCurrent","Security":{"Read":"RobloxScriptSecurity","Write":"RobloxScriptSecurity"},"Serialization":{"CanLoad":false,"CanSave":false},"Tags":["Hidden","ReadOnly","NotReplicated"],"ThreadSafety":"ReadSafe","ValueType":{"Category":"Primitive","Name":"bool"}},{"Category":"Data","MemberType":"Property","Name":"MultipleDocumentInterfaceInstance","Security":{"Read":"RobloxScriptSecurity","Write":"RobloxScriptSecurity"},"Serialization":{"CanLoad":false,"CanSave":false},"Tags":["Hidden","ReadOnly","NotReplicated"],"ThreadSafety":"ReadSafe","ValueType":{"Category":"Class","Name":"MultipleDocumentInterfaceInstance"}},{"Category":"Behavior","MemberType":"Property","Name":"UsesAssetInsertionDrag","Security":{"Read":"RobloxScriptSecurity","Write":"RobloxScriptSecurity"},"Serialization":{"CanLoad":false,"CanSave":false},"Tags":["Hidden","NotReplicated"],"ThreadSafety":"ReadSafe","ValueType":{"Category":"Primitive","Name":"bool"}},{"MemberType":"Function","Name":"Activate","Parameters":[{"Name":"exclusiveMouse","Type":{"Category":"Primitive","Name":"bool"}}],"ReturnType":{"Category":"Primitive","Name":"void"},"Security":"PluginSecurity","ThreadSafety":"Unsafe"},{"MemberType":"Function","Name":"CreatePluginAction","Parameters":[{"Name":"actionId","Type":{"Category":"Primitive","Name":"string"}},{"Name":"text","Type":{"Category":"Primitive","Name":"string"}},{"Name":"statusTip","Type":{"Category":"Primitive","Name":"string"}},{"Default":"","Name":"iconName","Type":{"Category":"Primitive","Name":"string"}},{"Default":"true","Name":"allowBinding","Type":{"Category":"Primitive","Name":"bool"}}],"ReturnType":{"Category":"Class","Name":"PluginAction"},"Security":"PluginSecurity","ThreadSafety":"Unsafe"},{"MemberType":"Function","Name":"CreatePluginMenu","Parameters":[{"Name":"id","Type":{"Category":"Primitive","Name":"string"}},{"Default":"","Name":"title","Type":{"Category":"Primitive","Name":"string"}},{"Default":"","Name":"icon","Type":{"Category":"Primitive","Name":"string"}}],"ReturnType":{"Category":"Class","Name":"PluginMenu"},"Security":"PluginSecurity","ThreadSafety":"Unsafe"},{"MemberType":"Function","Name":"CreateToolbar","Parameters":[{"Name":"name","Type":{"Category":"Primitive","Name":"string"}}],"ReturnType":{"Category":"Class","Name":"PluginToolbar"},"Security":"PluginSecurity","ThreadSafety":"Unsafe"},{"MemberType":"Function","Name":"Deactivate","Parameters":[],"ReturnType":{"Category":"Primitive","Name":"void"},"Security":"PluginSecurity","ThreadSafety":"Unsafe"},{"MemberType":"Function","Name":"GetItem","Parameters":[{"Name":"key","Type":{"Category":"Primitive","Name":"string"}},{"Name":"defaultValue","Type":{"Category":"Group","Name":"Variant"}}],"ReturnType":{"Category":"Group","Name":"Variant"},"Security":"RobloxScriptSecurity","ThreadSafety":"Unsafe"},{"MemberType":"Function","Name":"GetJoinMode","Parameters":[],"ReturnType":{"Category":"Enum","Name":"JointCreationMode"},"Security":"PluginSecurity","ThreadSafety":"Unsafe"},{"MemberType":"Function","Name":"GetMouse","Parameters":[],"ReturnType":{"Category":"Class","Name":"PluginMouse"},"Security":"PluginSecurity","ThreadSafety":"Unsafe"},{"MemberType":"Function","Name":"GetSelectedRibbonTool","Parameters":[],"ReturnType":{"Category":"Enum","Name":"RibbonTool"},"Security":"PluginSecurity","ThreadSafety":"Unsafe"},{"MemberType":"Function","Name":"GetSetting","Parameters":[{"Name":"key","Type":{"Category":"Primitive","Name":"string"}}],"ReturnType":{"Category":"Group","Name":"Variant"},"Security":"PluginSecurity","ThreadSafety":"Unsafe"},{"MemberType":"Function","Name":"GetStudioUserId","Parameters":[],"ReturnType":{"Category":"Primitive","Name":"int64"},"Security":"PluginSecurity","Tags":["Deprecated"],"ThreadSafety":"Unsafe"},{"MemberType":"Function","Name":"Invoke","Parameters":[{"Name":"key","Type":{"Category":"Primitive","Name":"string"}},{"Name":"arguments","Type":{"Category":"Group","Name":"Tuple"}}],"ReturnType":{"Category":"Primitive","Name":"void"},"Security":"RobloxScriptSecurity","ThreadSafety":"Unsafe"},{"MemberType":"Function","Name":"IsActivated","Parameters":[],"ReturnType":{"Category":"Primitive","Name":"bool"},"Security":"PluginSecurity","ThreadSafety":"Unsafe"},{"MemberType":"Function","Name":"IsActivatedWithExclusiveMouse","Parameters":[],"ReturnType":{"Category":"Primitive","Name":"bool"},"Security":"PluginSecurity","ThreadSafety":"Unsafe"},{"MemberType":"Function","Name":"Negate","Parameters":[{"Name":"objects","Type":{"Category":"DataType","Name":"Objects"}}],"ReturnType":{"Category":"DataType","Name":"Objects"},"Security":"PluginSecurity","ThreadSafety":"Unsafe"},{"MemberType":"Function","Name":"OnInvoke","Parameters":[{"Name":"key","Type":{"Category":"Primitive","Name":"string"}},{"Name":"callback","Type":{"Category":"DataType","Name":"Function"}}],"ReturnType":{"Category":"Class","Name":"Instance"},"Security":"RobloxScriptSecurity","ThreadSafety":"Unsafe"},{"MemberType":"Function","Name":"OnSetItem","Parameters":[{"Name":"key","Type":{"Category":"Primitive","Name":"string"}},{"Name":"callback","Type":{"Category":"DataType","Name":"Function"}}],"ReturnType":{"Category":"Class","Name":"Instance"},"Security":"RobloxScriptSecurity","ThreadSafety":"Unsafe"},{"MemberType":"Function","Name":"OpenScript","Parameters":[{"Name":"script","Type":{"Category":"Class","Name":"LuaSourceContainer"}},{"Default":"1","Name":"lineNumber","Type":{"Category":"Primitive","Name":"int"}}],"ReturnType":{"Category":"Primitive","Name":"void"},"Security":"PluginSecurity","ThreadSafety":"Unsafe"},{"MemberType":"Function","Name":"OpenWikiPage","Parameters":[{"Name":"url","Type":{"Category":"Primitive","Name":"string"}}],"ReturnType":{"Category":"Primitive","Name":"void"},"Security":"PluginSecurity","ThreadSafety":"Unsafe"},{"MemberType":"Function","Name":"PauseSound","Parameters":[{"Name":"sound","Type":{"Category":"Class","Name":"Instance"}}],"ReturnType":{"Category":"Primitive","Name":"void"},"Security":"RobloxScriptSecurity","ThreadSafety":"Unsafe"},{"MemberType":"Function","Name":"PlaySound","Parameters":[{"Name":"sound","Type":{"Category":"Class","Name":"Instance"}},{"Default":"0","Name":"normalizedTimePosition","Type":{"Category":"Primitive","Name":"double"}}],"ReturnType":{"Category":"Primitive","Name":"void"},"Security":"RobloxScriptSecurity","ThreadSafety":"Unsafe"},{"MemberType":"Function","Name":"ResumeSound","Parameters":[{"Name":"sound","Type":{"Category":"Class","Name":"Instance"}}],"ReturnType":{"Category":"Primitive","Name":"void"},"Security":"RobloxScriptSecurity","ThreadSafety":"Unsafe"},{"MemberType":"Function","Name":"SaveSelectedToRoblox","Parameters":[],"ReturnType":{"Category":"Primitive","Name":"void"},"Security":"PluginSecurity","ThreadSafety":"Unsafe"},{"MemberType":"Function","Name":"SelectRibbonTool","Parameters":[{"Name":"tool","Type":{"Category":"Enum","Name":"RibbonTool"}},{"Name":"position","Type":{"Category":"DataType","Name":"UDim2"}}],"ReturnType":{"Category":"Primitive","Name":"void"},"Security":"PluginSecurity","ThreadSafety":"Unsafe"},{"MemberType":"Function","Name":"Separate","Parameters":[{"Name":"objects","Type":{"Category":"DataType","Name":"Objects"}}],"ReturnType":{"Category":"DataType","Name":"Objects"},"Security":"PluginSecurity","ThreadSafety":"Unsafe"},{"MemberType":"Function","Name":"SetItem","Parameters":[{"Name":"key","Type":{"Category":"Primitive","Name":"string"}},{"Name":"value","Type":{"Category":"Group","Name":"Variant"}}],"ReturnType":{"Category":"Primitive","Name":"void"},"Security":"RobloxScriptSecurity","ThreadSafety":"Unsafe"},{"MemberType":"Function","Name":"SetReady","Parameters":[],"ReturnType":{"Category":"Primitive","Name":"void"},"Security":"RobloxScriptSecurity","ThreadSafety":"Unsafe"},{"MemberType":"Function","Name":"SetSetting","Parameters":[{"Name":"key","Type":{"Category":"Primitive","Name":"string"}},{"Name":"value","Type":{"Category":"Group","Name":"Variant"}}],"ReturnType":{"Category":"Primitive","Name":"void"},"Security":"PluginSecurity","ThreadSafety":"Unsafe"},{"MemberType":"Function","Name":"StartDecalDrag","Parameters":[{"Name":"decal","Type":{"Category":"Class","Name":"Instance"}}],"ReturnType":{"Category":"Primitive","Name":"void"},"Security":"RobloxScriptSecurity","ThreadSafety":"Unsafe"},{"MemberType":"Function","Name":"StartDrag","Parameters":[{"Name":"dragData","Type":{"Category":"Group","Name":"Dictionary"}}],"ReturnType":{"Category":"Primitive","Name":"void"},"Security":"PluginSecurity","ThreadSafety":"Unsafe"},{"MemberType":"Function","Name":"StopAllSounds","Parameters":[],"ReturnType":{"Category":"Primitive","Name":"void"},"Security":"RobloxScriptSecurity","ThreadSafety":"Unsafe"},{"MemberType":"Function","Name":"Union","Parameters":[{"Name":"objects","Type":{"Category":"DataType","Name":"Objects"}}],"ReturnType":{"Category":"Class","Name":"Instance"},"Security":"PluginSecurity","ThreadSafety":"Unsafe"},{"MemberType":"Function","Name":"CreateDockWidgetPluginGui","Parameters":[{"Name":"pluginGuiId","Type":{"Category":"Primitive","Name":"string"}},{"Name":"dockWidgetPluginGuiInfo","Type":{"Category":"DataType","Name":"DockWidgetPluginGuiInfo"}}],"ReturnType":{"Category":"Class","Name":"DockWidgetPluginGui"},"Security":"PluginSecurity","Tags":["Yields"],"ThreadSafety":"Unsafe"},{"MemberType":"Function","Name":"CreateQWidgetPluginGui","Parameters":[{"Name":"pluginGuiId","Type":{"Category":"Primitive","Name":"string"}},{"Name":"pluginGuiOptions","Type":{"Category":"Group","Name":"Dictionary"}}],"ReturnType":{"Category":"Class","Name":"QWidgetPluginGui"},"Security":"RobloxScriptSecurity","Tags":["Yields"],"ThreadSafety":"Unsafe"},{"MemberType":"Function","Name":"ImportFbxAnimation","Parameters":[{"Name":"rigModel","Type":{"Category":"Class","Name":"Instance"}},{"Default":"true","Name":"isR15","Type":{"Category":"Primitive","Name":"bool"}}],"ReturnType":{"Category":"Class","Name":"Instance"},"Security":"PluginSecurity","Tags":["Yields"],"ThreadSafety":"Unsafe"},{"MemberType":"Function","Name":"ImportFbxRig","Parameters":[{"Default":"true","Name":"isR15","Type":{"Category":"Primitive","Name":"bool"}}],"ReturnType":{"Category":"Class","Name":"Instance"},"Security":"PluginSecurity","Tags":["Yields"],"ThreadSafety":"Unsafe"},{"MemberType":"Function","Name":"PromptForExistingAssetId","Parameters":[{"Name":"assetType","Type":{"Category":"Primitive","Name":"string"}}],"ReturnType":{"Category":"Primitive","Name":"int64"},"Security":"PluginSecurity","Tags":["Yields"],"ThreadSafety":"Unsafe"},{"MemberType":"Function","Name":"PromptSaveSelection","Parameters":[{"Default":"","Name":"suggestedFileName","Type":{"Category":"Primitive","Name":"string"}}],"ReturnType":{"Category":"Primitive","Name":"bool"},"Security":"PluginSecurity","Tags":["Yields"],"ThreadSafety":"Unsafe"},{"MemberType":"Event","Name":"Deactivation","Parameters":[],"Security":"PluginSecurity","ThreadSafety":"Unsafe"},{"MemberType":"Event","Name":"Ready","Parameters":[],"Security":"RobloxScriptSecurity","ThreadSafety":"Unsafe"},{"MemberType":"Event","Name":"Unloading","Parameters":[],"Security":"PluginSecurity","ThreadSafety":"Unsafe"},{"MemberType":"Callback","Name":"ProcessAssetInsertionDrag","Parameters":[{"Name":"assetId","Type":{"Category":"Primitive","Name":"string"}},{"Name":"assetTypeId","Type":{"Category":"Primitive","Name":"int"}},{"Name":"instances","Type":{"Category":"DataType","Name":"Objects"}}],"ReturnType":{"Category":"DataType","Name":"Objects"},"Security":"RobloxScriptSecurity","Tags":["NoYield"],"ThreadSafety":"Unsafe"},{"MemberType":"Callback","Name":"ProcessAssetInsertionDrop","Parameters":[],"ReturnType":{"Category":"Primitive","Name":"void"},"Security":"RobloxScriptSecurity","Tags":["NoYield"],"ThreadSafety":"Unsafe"}],"MemoryCategory":"Instances","Name":"Plugin","Superclass":"Instance","Tags":["NotCreatable"]},{"Members":[{"Category":"Data","MemberType":"Property","Name":"ActionId","Security":{"Read":"None","Write":"None"},"Serialization":{"CanLoad":false,"CanSave":false},"Tags":["ReadOnly","NotReplicated"],"ThreadSafety":"ReadSafe","ValueType":{"Category":"Primitive","Name":"string"}},{"Category":"Data","MemberType":"Property","Name":"AllowBinding","Security":{"Read":"None","Write":"None"},"Serialization":{"CanLoad":false,"CanSave":false},"Tags":["ReadOnly","NotReplicated"],"ThreadSafety":"ReadSafe","ValueType":{"Category":"Primitive","Name":"bool"}},{"Category":"Data","MemberType":"Property","Name":"Checked","Security":{"Read":"RobloxScriptSecurity","Write":"RobloxScriptSecurity"},"Serialization":{"CanLoad":false,"CanSave":false},"Tags":["Hidden","NotReplicated"],"ThreadSafety":"ReadSafe","ValueType":{"Category":"Primitive","Name":"bool"}},{"Category":"Data","MemberType":"Property","Name":"DefaultShortcut","Security":{"Read":"RobloxScriptSecurity","Write":"RobloxScriptSecurity"},"Serialization":{"CanLoad":false,"CanSave":false},"Tags":["Hidden","NotReplicated"],"ThreadSafety":"ReadSafe","ValueType":{"Category":"Primitive","Name":"string"}},{"Category":"Data","MemberType":"Property","Name":"Enabled","Security":{"Read":"RobloxScriptSecurity","Write":"RobloxScriptSecurity"},"Serialization":{"CanLoad":false,"CanSave":false},"Tags":["Hidden","NotReplicated"],"ThreadSafety":"ReadSafe","ValueType":{"Category":"Primitive","Name":"bool"}},{"Category":"Data","MemberType":"Property","Name":"StatusTip","Security":{"Read":"None","Write":"None"},"Serialization":{"CanLoad":false,"CanSave":false},"Tags":["ReadOnly","NotReplicated"],"ThreadSafety":"ReadSafe","ValueType":{"Category":"Primitive","Name":"string"}},{"Category":"Data","MemberType":"Property","Name":"Text","Security":{"Read":"None","Write":"None"},"Serialization":{"CanLoad":false,"CanSave":false},"Tags":["ReadOnly","NotReplicated"],"ThreadSafety":"ReadSafe","ValueType":{"Category":"Primitive","Name":"string"}},{"MemberType":"Event","Name":"Triggered","Parameters":[],"Security":"PluginSecurity","ThreadSafety":"Unsafe"}],"MemoryCategory":"Instances","Name":"PluginAction","Superclass":"Instance","Tags":["NotReplicated"]},{"Members":[],"MemoryCategory":"Instances","Name":"PluginDebugService","Superclass":"Instance","Tags":["NotCreatable","Service","NotReplicated"]},{"Members":[{"Category":"Data","MemberType":"Property","Name":"Data","Security":{"Read":"None","Write":"None"},"Serialization":{"CanLoad":false,"CanSave":false},"Tags":["ReadOnly","NotReplicated"],"ThreadSafety":"ReadSafe","ValueType":{"Category":"Primitive","Name":"string"}},{"Category":"Data","MemberType":"Property","Name":"MimeType","Security":{"Read":"None","Write":"None"},"Serialization":{"CanLoad":false,"CanSave":false},"Tags":["ReadOnly","NotReplicated"],"ThreadSafety":"ReadSafe","ValueType":{"Category":"Primitive","Name":"string"}},{"Category":"Data","MemberType":"Property","Name":"Position","Security":{"Read":"None","Write":"None"},"Serialization":{"CanLoad":false,"CanSave":false},"Tags":["ReadOnly","NotReplicated"],"ThreadSafety":"ReadSafe","ValueType":{"Category":"DataType","Name":"Vector2"}},{"Category":"Data","MemberType":"Property","Name":"Sender","Security":{"Read":"None","Write":"None"},"Serialization":{"CanLoad":false,"CanSave":false},"Tags":["ReadOnly","NotReplicated"],"ThreadSafety":"ReadSafe","ValueType":{"Category":"Primitive","Name":"string"}}],"MemoryCategory":"Instances","Name":"PluginDragEvent","Superclass":"Instance","Tags":["NotCreatable","NotReplicated"]},{"Members":[],"MemoryCategory":"Instances","Name":"PluginGuiService","Superclass":"Instance","Tags":["NotCreatable","Service","NotReplicated"]},{"Members":[{"MemberType":"Function","Name":"SetAutoUpdate","Parameters":[{"Name":"pluginId","Type":{"Category":"Primitive","Name":"int64"}},{"Name":"state","Type":{"Category":"Primitive","Name":"bool"}}],"ReturnType":{"Category":"Primitive","Name":"void"},"Security":"RobloxScriptSecurity","ThreadSafety":"Unsafe"}],"MemoryCategory":"Instances","Name":"PluginManagementService","Superclass":"Instance","Tags":["NotCreatable","Service","NotReplicated"]},{"Members":[{"MemberType":"Function","Name":"CreatePlugin","Parameters":[],"ReturnType":{"Category":"Class","Name":"Instance"},"Security":"PluginSecurity","Tags":["Deprecated","CustomLuaState"],"ThreadSafety":"Unsafe"},{"MemberType":"Function","Name":"ExportPlace","Parameters":[{"Default":"","Name":"filePath","Type":{"Category":"Primitive","Name":"string"}}],"ReturnType":{"Category":"Primitive","Name":"void"},"Security":"PluginSecurity","ThreadSafety":"Unsafe"},{"MemberType":"Function","Name":"ExportSelection","Parameters":[{"Default":"","Name":"filePath","Type":{"Category":"Primitive","Name":"string"}}],"ReturnType":{"Category":"Primitive","Name":"void"},"Security":"PluginSecurity","ThreadSafety":"Unsafe"}],"MemoryCategory":"Instances","Name":"PluginManager","Superclass":"Instance","Tags":["NotCreatable"]},{"Members":[{"MemberType":"Function","Name":"CreatePlugin","Parameters":[],"ReturnType":{"Category":"Class","Name":"Instance"},"Security":"PluginSecurity","Tags":["Deprecated","CustomLuaState"],"ThreadSafety":"Unsafe"},{"MemberType":"Function","Name":"ExportPlace","Parameters":[{"Default":"","Name":"filePath","Type":{"Category":"Primitive","Name":"string"}}],"ReturnType":{"Category":"Primitive","Name":"void"},"Security":"PluginSecurity","ThreadSafety":"Unsafe"},{"MemberType":"Function","Name":"ExportSelection","Parameters":[{"Default":"","Name":"filePath","Type":{"Category":"Primitive","Name":"string"}}],"ReturnType":{"Category":"Primitive","Name":"void"},"Security":"PluginSecurity","ThreadSafety":"Unsafe"}],"MemoryCategory":"Instances","Name":"PluginManagerInterface","Superclass":"Instance","Tags":["NotCreatable","NotReplicated"]},{"Members":[{"Category":"Appearance","MemberType":"Property","Name":"Icon","Security":{"Read":"None","Write":"None"},"Serialization":{"CanLoad":true,"CanSave":false},"Tags":["NotReplicated"],"ThreadSafety":"ReadSafe","ValueType":{"Category":"Primitive","Name":"string"}},{"Category":"Appearance","MemberType":"Property","Name":"Title","Security":{"Read":"None","Write":"None"},"Serialization":{"CanLoad":true,"CanSave":false},"Tags":["NotReplicated"],"ThreadSafety":"ReadSafe","ValueType":{"Category":"Primitive","Name":"string"}},{"MemberType":"Function","Name":"AddAction","Parameters":[{"Name":"action","Type":{"Category":"Class","Name":"Instance"}}],"ReturnType":{"Category":"Primitive","Name":"void"},"Security":"PluginSecurity","ThreadSafety":"Unsafe"},{"MemberType":"Function","Name":"AddMenu","Parameters":[{"Name":"menu","Type":{"Category":"Class","Name":"Instance"}}],"ReturnType":{"Category":"Primitive","Name":"void"},"Security":"PluginSecurity","ThreadSafety":"Unsafe"},{"MemberType":"Function","Name":"AddNewAction","Parameters":[{"Name":"actionId","Type":{"Category":"Primitive","Name":"string"}},{"Name":"text","Type":{"Category":"Primitive","Name":"string"}},{"Default":"","Name":"icon","Type":{"Category":"Primitive","Name":"string"}}],"ReturnType":{"Category":"Class","Name":"Instance"},"Security":"PluginSecurity","ThreadSafety":"Unsafe"},{"MemberType":"Function","Name":"AddSeparator","Parameters":[],"ReturnType":{"Category":"Primitive","Name":"void"},"Security":"PluginSecurity","ThreadSafety":"Unsafe"},{"MemberType":"Function","Name":"Clear","Parameters":[],"ReturnType":{"Category":"Primitive","Name":"void"},"Security":"PluginSecurity","ThreadSafety":"Unsafe"},{"MemberType":"Function","Name":"ShowAsync","Parameters":[],"ReturnType":{"Category":"Class","Name":"Instance"},"Security":"PluginSecurity","Tags":["Yields"],"ThreadSafety":"Unsafe"}],"MemoryCategory":"Instances","Name":"PluginMenu","Superclass":"Instance","Tags":["NotCreatable","NotReplicated"]},{"Members":[{"MemberType":"Function","Name":"GetPluginPolicy","Parameters":[{"Name":"pluginName","Type":{"Category":"Primitive","Name":"string"}}],"ReturnType":{"Category":"Group","Name":"Dictionary"},"Security":"RobloxScriptSecurity","ThreadSafety":"Unsafe"}],"MemoryCategory":"Instances","Name":"PluginPolicyService","Superclass":"Instance","Tags":["NotCreatable","Service","NotReplicated"]},{"Members":[{"MemberType":"Function","Name":"CreateButton","Parameters":[{"Name":"buttonId","Type":{"Category":"Primitive","Name":"string"}},{"Name":"tooltip","Type":{"Category":"Primitive","Name":"string"}},{"Name":"iconname","Type":{"Category":"Primitive","Name":"string"}},{"Default":"","Name":"text","Type":{"Category":"Primitive","Name":"string"}}],"ReturnType":{"Category":"Class","Name":"Instance"},"Security":"PluginSecurity","ThreadSafety":"Unsafe"}],"MemoryCategory":"Instances","Name":"PluginToolbar","Superclass":"Instance","Tags":["NotCreatable"]},{"Members":[{"Category":"Appearance","MemberType":"Property","Name":"ClickableWhenViewportHidden","Security":{"Read":"None","Write":"None"},"Serialization":{"CanLoad":true,"CanSave":false},"Tags":["NotReplicated"],"ThreadSafety":"ReadSafe","ValueType":{"Category":"Primitive","Name":"bool"}},{"Category":"Appearance","MemberType":"Property","Name":"Enabled","Security":{"Read":"None","Write":"None"},"Serialization":{"CanLoad":true,"CanSave":false},"Tags":["NotReplicated"],"ThreadSafety":"ReadSafe","ValueType":{"Category":"Primitive","Name":"bool"}},{"Category":"Appearance","MemberType":"Property","Name":"Icon","Security":{"Read":"None","Write":"None"},"Serialization":{"CanLoad":true,"CanSave":false},"Tags":["NotReplicated"],"ThreadSafety":"ReadSafe","ValueType":{"Category":"DataType","Name":"Content"}},{"MemberType":"Function","Name":"SetActive","Parameters":[{"Name":"active","Type":{"Category":"Primitive","Name":"bool"}}],"ReturnType":{"Category":"Primitive","Name":"void"},"Security":"PluginSecurity","ThreadSafety":"Unsafe"},{"MemberType":"Event","Name":"Click","Parameters":[],"Security":"PluginSecurity","ThreadSafety":"Unsafe"}],"MemoryCategory":"Instances","Name":"PluginToolbarButton","Superclass":"Instance","Tags":["NotCreatable"]},{"Members":[{"MemberType":"Function","Name":"GetAwardablePoints","Parameters":[],"ReturnType":{"Category":"Primitive","Name":"int"},"Security":"None","Tags":["Deprecated"],"ThreadSafety":"Unsafe"},{"MemberType":"Function","Name":"AwardPoints","Parameters":[{"Name":"userId","Type":{"Category":"Primitive","Name":"int64"}},{"Name":"amount","Type":{"Category":"Primitive","Name":"int"}}],"ReturnType":{"Category":"Group","Name":"Tuple"},"Security":"None","Tags":["Yields","Deprecated"],"ThreadSafety":"Unsafe"},{"MemberType":"Function","Name":"GetGamePointBalance","Parameters":[{"Name":"userId","Type":{"Category":"Primitive","Name":"int64"}}],"ReturnType":{"Category":"Primitive","Name":"int"},"Security":"None","Tags":["Yields","Deprecated"],"ThreadSafety":"Unsafe"},{"MemberType":"Function","Name":"GetPointBalance","Parameters":[{"Name":"userId","Type":{"Category":"Primitive","Name":"int64"}}],"ReturnType":{"Category":"Primitive","Name":"int"},"Security":"None","Tags":["Yields","Deprecated"],"ThreadSafety":"Unsafe"},{"MemberType":"Event","Name":"PointsAwarded","Parameters":[{"Name":"userId","Type":{"Category":"Primitive","Name":"int64"}},{"Name":"pointsAwarded","Type":{"Category":"Primitive","Name":"int"}},{"Name":"userBalanceInGame","Type":{"Category":"Primitive","Name":"int"}},{"Name":"userTotalBalance","Type":{"Category":"Primitive","Name":"int"}}],"Security":"None","ThreadSafety":"Unsafe"}],"MemoryCategory":"Instances","Name":"PointsService","Superclass":"Instance","Tags":["NotCreatable","Service","Deprecated"]},{"Members":[{"Category":"Data","MemberType":"Property","Name":"IsLuobuServer","Security":{"Read":"RobloxScriptSecurity","Write":"RobloxScriptSecurity"},"Serialization":{"CanLoad":true,"CanSave":true},"Tags":["Hidden"],"ThreadSafety":"ReadSafe","ValueType":{"Category":"Enum","Name":"TriStateBoolean"}},{"Category":"Data","MemberType":"Property","Name":"LuobuWhitelisted","Security":{"Read":"RobloxScriptSecurity","Write":"RobloxScriptSecurity"},"Serialization":{"CanLoad":true,"CanSave":true},"Tags":["Hidden"],"ThreadSafety":"ReadSafe","ValueType":{"Category":"Enum","Name":"TriStateBoolean"}},{"MemberType":"Function","Name":"GetPolicyInfoForPlayerAsync","Parameters":[{"Name":"player","Type":{"Category":"Class","Name":"Instance"}}],"ReturnType":{"Category":"Group","Name":"Dictionary"},"Security":"None","Tags":["Yields"],"ThreadSafety":"Unsafe"},{"MemberType":"Function","Name":"GetPolicyInfoForServerRobloxOnlyAsync","Parameters":[],"ReturnType":{"Category":"Group","Name":"Dictionary"},"Security":"RobloxScriptSecurity","Tags":["Yields"],"ThreadSafety":"Unsafe"}],"MemoryCategory":"Instances","Name":"PolicyService","Superclass":"Instance","Tags":["NotCreatable","Service","NotReplicated"]},{"Members":[{"Category":"Data","MemberType":"Property","Name":"EasingDirection","Security":{"Read":"None","Write":"None"},"Serialization":{"CanLoad":true,"CanSave":true},"ThreadSafety":"ReadSafe","ValueType":{"Category":"Enum","Name":"PoseEasingDirection"}},{"Category":"Data","MemberType":"Property","Name":"EasingStyle","Security":{"Read":"None","Write":"None"},"Serialization":{"CanLoad":true,"CanSave":true},"ThreadSafety":"ReadSafe","ValueType":{"Category":"Enum","Name":"PoseEasingStyle"}},{"Category":"Data","MemberType":"Property","Name":"Weight","Security":{"Read":"None","Write":"None"},"Serialization":{"CanLoad":true,"CanSave":true},"ThreadSafety":"ReadSafe","ValueType":{"Category":"Primitive","Name":"float"}}],"MemoryCategory":"Instances","Name":"PoseBase","Superclass":"Instance","Tags":["NotCreatable"]},{"Members":[{"Category":"Data","MemberType":"Property","Name":"Value","Security":{"Read":"None","Write":"None"},"Serialization":{"CanLoad":true,"CanSave":true},"ThreadSafety":"ReadSafe","ValueType":{"Category":"Primitive","Name":"double"}}],"MemoryCategory":"Animation","Name":"NumberPose","Superclass":"PoseBase"},{"Members":[{"Category":"Data","MemberType":"Property","Name":"CFrame","Security":{"Read":"None","Write":"None"},"Serialization":{"CanLoad":true,"CanSave":true},"ThreadSafety":"ReadSafe","ValueType":{"Category":"DataType","Name":"CFrame"}},{"Category":"Data","MemberType":"Property","Name":"MaskWeight","Security":{"Read":"None","Write":"None"},"Serialization":{"CanLoad":true,"CanSave":false},"Tags":["NotReplicated","Deprecated"],"ThreadSafety":"ReadSafe","ValueType":{"Category":"Primitive","Name":"float"}},{"MemberType":"Function","Name":"AddSubPose","Parameters":[{"Name":"pose","Type":{"Category":"Class","Name":"Instance"}}],"ReturnType":{"Category":"Primitive","Name":"void"},"Security":"None","ThreadSafety":"Unsafe"},{"MemberType":"Function","Name":"GetSubPoses","Parameters":[],"ReturnType":{"Category":"DataType","Name":"Objects"},"Security":"None","ThreadSafety":"Unsafe"},{"MemberType":"Function","Name":"RemoveSubPose","Parameters":[{"Name":"pose","Type":{"Category":"Class","Name":"Instance"}}],"ReturnType":{"Category":"Primitive","Name":"void"},"Security":"None","ThreadSafety":"Unsafe"}],"MemoryCategory":"Animation","Name":"Pose","Superclass":"PoseBase"},{"Members":[{"Category":"State","MemberType":"Property","Name":"Enabled","Security":{"Read":"None","Write":"None"},"Serialization":{"CanLoad":true,"CanSave":true},"ThreadSafety":"ReadSafe","ValueType":{"Category":"Primitive","Name":"bool"}}],"MemoryCategory":"Instances","Name":"PostEffect","Superclass":"Instance","Tags":["NotCreatable"]},{"Members":[{"Category":"State","MemberType":"Property","Name":"Intensity","Security":{"Read":"None","Write":"None"},"Serialization":{"CanLoad":true,"CanSave":true},"ThreadSafety":"ReadSafe","ValueType":{"Category":"Primitive","Name":"float"}},{"Category":"State","MemberType":"Property","Name":"Size","Security":{"Read":"None","Write":"None"},"Serialization":{"CanLoad":true,"CanSave":true},"ThreadSafety":"ReadSafe","ValueType":{"Category":"Primitive","Name":"float"}},{"Category":"State","MemberType":"Property","Name":"Threshold","Security":{"Read":"None","Write":"None"},"Serialization":{"CanLoad":true,"CanSave":true},"ThreadSafety":"ReadSafe","ValueType":{"Category":"Primitive","Name":"float"}}],"MemoryCategory":"Instances","Name":"BloomEffect","Superclass":"PostEffect"},{"Members":[{"Category":"State","MemberType":"Property","Name":"Size","Security":{"Read":"None","Write":"None"},"Serialization":{"CanLoad":true,"CanSave":true},"ThreadSafety":"ReadSafe","ValueType":{"Category":"Primitive","Name":"float"}}],"MemoryCategory":"Instances","Name":"BlurEffect","Superclass":"PostEffect"},{"Members":[{"Category":"State","MemberType":"Property","Name":"Brightness","Security":{"Read":"None","Write":"None"},"Serialization":{"CanLoad":true,"CanSave":true},"ThreadSafety":"ReadSafe","ValueType":{"Category":"Primitive","Name":"float"}},{"Category":"State","MemberType":"Property","Name":"Contrast","Security":{"Read":"None","Write":"None"},"Serialization":{"CanLoad":true,"CanSave":true},"ThreadSafety":"ReadSafe","ValueType":{"Category":"Primitive","Name":"float"}},{"Category":"State","MemberType":"Property","Name":"Saturation","Security":{"Read":"None","Write":"None"},"Serialization":{"CanLoad":true,"CanSave":true},"ThreadSafety":"ReadSafe","ValueType":{"Category":"Primitive","Name":"float"}},{"Category":"State","MemberType":"Property","Name":"TintColor","Security":{"Read":"None","Write":"None"},"Serialization":{"CanLoad":true,"CanSave":true},"ThreadSafety":"ReadSafe","ValueType":{"Category":"DataType","Name":"Color3"}}],"MemoryCategory":"Instances","Name":"ColorCorrectionEffect","Superclass":"PostEffect"},{"Members":[{"Category":"State","MemberType":"Property","Name":"FarIntensity","Security":{"Read":"None","Write":"None"},"Serialization":{"CanLoad":true,"CanSave":true},"ThreadSafety":"ReadSafe","ValueType":{"Category":"Primitive","Name":"float"}},{"Category":"State","MemberType":"Property","Name":"FocusDistance","Security":{"Read":"None","Write":"None"},"Serialization":{"CanLoad":true,"CanSave":true},"ThreadSafety":"ReadSafe","ValueType":{"Category":"Primitive","Name":"float"}},{"Category":"State","MemberType":"Property","Name":"InFocusRadius","Security":{"Read":"None","Write":"None"},"Serialization":{"CanLoad":true,"CanSave":true},"ThreadSafety":"ReadSafe","ValueType":{"Category":"Primitive","Name":"float"}},{"Category":"State","MemberType":"Property","Name":"NearIntensity","Security":{"Read":"None","Write":"None"},"Serialization":{"CanLoad":true,"CanSave":true},"ThreadSafety":"ReadSafe","ValueType":{"Category":"Primitive","Name":"float"}}],"MemoryCategory":"Instances","Name":"DepthOfFieldEffect","Superclass":"PostEffect"},{"Members":[{"Category":"State","MemberType":"Property","Name":"Intensity","Security":{"Read":"None","Write":"None"},"Serialization":{"CanLoad":true,"CanSave":true},"ThreadSafety":"ReadSafe","ValueType":{"Category":"Primitive","Name":"float"}},{"Category":"State","MemberType":"Property","Name":"Spread","Security":{"Read":"None","Write":"None"},"Serialization":{"CanLoad":true,"CanSave":true},"ThreadSafety":"ReadSafe","ValueType":{"Category":"Primitive","Name":"float"}}],"MemoryCategory":"Instances","Name":"SunRaysEffect","Superclass":"PostEffect"},{"Members":[],"MemoryCategory":"Instances","Name":"ProcessInstancePhysicsService","Superclass":"Instance","Tags":["NotCreatable","Service"]},{"Members":[{"Category":"Data","MemberType":"Property","Name":"ActionText","Security":{"Read":"None","Write":"None"},"Serialization":{"CanLoad":true,"CanSave":true},"ThreadSafety":"ReadSafe","ValueType":{"Category":"Primitive","Name":"string"}},{"Category":"Localization","MemberType":"Property","Name":"AutoLocalize","Security":{"Read":"None","Write":"None"},"Serialization":{"CanLoad":true,"CanSave":true},"ThreadSafety":"ReadSafe","ValueType":{"Category":"Primitive","Name":"bool"}},{"Category":"Data","MemberType":"Property","Name":"ClickablePrompt","Security":{"Read":"None","Write":"None"},"Serialization":{"CanLoad":true,"CanSave":true},"ThreadSafety":"ReadSafe","ValueType":{"Category":"Primitive","Name":"bool"}},{"Category":"Data","MemberType":"Property","Name":"Enabled","Security":{"Read":"None","Write":"None"},"Serialization":{"CanLoad":true,"CanSave":true},"ThreadSafety":"ReadSafe","ValueType":{"Category":"Primitive","Name":"bool"}},{"Category":"Data","MemberType":"Property","Name":"Exclusivity","Security":{"Read":"None","Write":"None"},"Serialization":{"CanLoad":true,"CanSave":true},"ThreadSafety":"ReadSafe","ValueType":{"Category":"Enum","Name":"ProximityPromptExclusivity"}},{"Category":"Data","MemberType":"Property","Name":"GamepadKeyCode","Security":{"Read":"None","Write":"None"},"Serialization":{"CanLoad":true,"CanSave":true},"ThreadSafety":"ReadSafe","ValueType":{"Category":"Enum","Name":"KeyCode"}},{"Category":"Data","MemberType":"Property","Name":"HoldDuration","Security":{"Read":"None","Write":"None"},"Serialization":{"CanLoad":true,"CanSave":true},"ThreadSafety":"ReadSafe","ValueType":{"Category":"Primitive","Name":"float"}},{"Category":"Data","MemberType":"Property","Name":"KeyboardKeyCode","Security":{"Read":"None","Write":"None"},"Serialization":{"CanLoad":true,"CanSave":true},"ThreadSafety":"ReadSafe","ValueType":{"Category":"Enum","Name":"KeyCode"}},{"Category":"Data","MemberType":"Property","Name":"MaxActivationDistance","Security":{"Read":"None","Write":"None"},"Serialization":{"CanLoad":true,"CanSave":true},"ThreadSafety":"ReadSafe","ValueType":{"Category":"Primitive","Name":"float"}},{"Category":"Data","MemberType":"Property","Name":"ObjectText","Security":{"Read":"None","Write":"None"},"Serialization":{"CanLoad":true,"CanSave":true},"ThreadSafety":"ReadSafe","ValueType":{"Category":"Primitive","Name":"string"}},{"Category":"Data","MemberType":"Property","Name":"RequiresLineOfSight","Security":{"Read":"None","Write":"None"},"Serialization":{"CanLoad":true,"CanSave":true},"ThreadSafety":"ReadSafe","ValueType":{"Category":"Primitive","Name":"bool"}},{"Category":"Localization","MemberType":"Property","Name":"RootLocalizationTable","Security":{"Read":"None","Write":"None"},"Serialization":{"CanLoad":true,"CanSave":true},"ThreadSafety":"ReadSafe","ValueType":{"Category":"Class","Name":"LocalizationTable"}},{"Category":"Data","MemberType":"Property","Name":"Style","Security":{"Read":"None","Write":"None"},"Serialization":{"CanLoad":true,"CanSave":true},"ThreadSafety":"ReadSafe","ValueType":{"Category":"Enum","Name":"ProximityPromptStyle"}},{"Category":"Data","MemberType":"Property","Name":"UIOffset","Security":{"Read":"None","Write":"None"},"Serialization":{"CanLoad":true,"CanSave":true},"ThreadSafety":"ReadSafe","ValueType":{"Category":"DataType","Name":"Vector2"}},{"MemberType":"Function","Name":"InputHoldBegin","Parameters":[],"ReturnType":{"Category":"Primitive","Name":"void"},"Security":"None","ThreadSafety":"Unsafe"},{"MemberType":"Function","Name":"InputHoldEnd","Parameters":[],"ReturnType":{"Category":"Primitive","Name":"void"},"Security":"None","ThreadSafety":"Unsafe"},{"MemberType":"Event","Name":"PromptButtonHoldBegan","Parameters":[{"Name":"playerWhoTriggered","Type":{"Category":"Class","Name":"Player"}}],"Security":"None","ThreadSafety":"Unsafe"},{"MemberType":"Event","Name":"PromptButtonHoldEnded","Parameters":[{"Name":"playerWhoTriggered","Type":{"Category":"Class","Name":"Player"}}],"Security":"None","ThreadSafety":"Unsafe"},{"MemberType":"Event","Name":"PromptHidden","Parameters":[],"Security":"None","ThreadSafety":"Unsafe"},{"MemberType":"Event","Name":"PromptShown","Parameters":[{"Name":"inputType","Type":{"Category":"Enum","Name":"ProximityPromptInputType"}}],"Security":"None","ThreadSafety":"Unsafe"},{"MemberType":"Event","Name":"TriggerEnded","Parameters":[{"Name":"playerWhoTriggered","Type":{"Category":"Class","Name":"Player"}}],"Security":"None","ThreadSafety":"Unsafe"},{"MemberType":"Event","Name":"Triggered","Parameters":[{"Name":"playerWhoTriggered","Type":{"Category":"Class","Name":"Player"}}],"Security":"None","ThreadSafety":"Unsafe"}],"MemoryCategory":"Instances","Name":"ProximityPrompt","Superclass":"Instance"},{"Members":[{"Category":"Data","MemberType":"Property","Name":"Enabled","Security":{"Read":"None","Write":"None"},"Serialization":{"CanLoad":true,"CanSave":true},"ThreadSafety":"ReadSafe","ValueType":{"Category":"Primitive","Name":"bool"}},{"Category":"Data","MemberType":"Property","Name":"MaxPromptsVisible","Security":{"Read":"None","Write":"None"},"Serialization":{"CanLoad":true,"CanSave":true},"ThreadSafety":"ReadSafe","ValueType":{"Category":"Primitive","Name":"int"}},{"MemberType":"Event","Name":"PromptButtonHoldBegan","Parameters":[{"Name":"prompt","Type":{"Category":"Class","Name":"ProximityPrompt"}},{"Name":"playerWhoTriggered","Type":{"Category":"Class","Name":"Player"}}],"Security":"None","ThreadSafety":"Unsafe"},{"MemberType":"Event","Name":"PromptButtonHoldEnded","Parameters":[{"Name":"prompt","Type":{"Category":"Class","Name":"ProximityPrompt"}},{"Name":"playerWhoTriggered","Type":{"Category":"Class","Name":"Player"}}],"Security":"None","ThreadSafety":"Unsafe"},{"MemberType":"Event","Name":"PromptHidden","Parameters":[{"Name":"prompt","Type":{"Category":"Class","Name":"ProximityPrompt"}}],"Security":"None","ThreadSafety":"Unsafe"},{"MemberType":"Event","Name":"PromptShown","Parameters":[{"Name":"prompt","Type":{"Category":"Class","Name":"ProximityPrompt"}},{"Name":"inputType","Type":{"Category":"Enum","Name":"ProximityPromptInputType"}}],"Security":"None","ThreadSafety":"Unsafe"},{"MemberType":"Event","Name":"PromptTriggerEnded","Parameters":[{"Name":"prompt","Type":{"Category":"Class","Name":"ProximityPrompt"}},{"Name":"playerWhoTriggered","Type":{"Category":"Class","Name":"Player"}}],"Security":"None","ThreadSafety":"Unsafe"},{"MemberType":"Event","Name":"PromptTriggered","Parameters":[{"Name":"prompt","Type":{"Category":"Class","Name":"ProximityPrompt"}},{"Name":"playerWhoTriggered","Type":{"Category":"Class","Name":"Player"}}],"Security":"None","ThreadSafety":"Unsafe"}],"MemoryCategory":"Instances","Name":"ProximityPromptService","Superclass":"Instance","Tags":["Service","NotBrowsable"]},{"Members":[{"MemberType":"Function","Name":"PublishDescendantAssets","Parameters":[{"Name":"instance","Type":{"Category":"Class","Name":"Instance"}}],"ReturnType":{"Category":"Primitive","Name":"bool"},"Security":"RobloxScriptSecurity","ThreadSafety":"Unsafe"},{"MemberType":"Function","Name":"PublishCageMeshAsync","Parameters":[{"Name":"wrap","Type":{"Category":"Class","Name":"Instance"}},{"Name":"cageType","Type":{"Category":"Enum","Name":"CageType"}}],"ReturnType":{"Category":"DataType","Name":"Content"},"Security":"RobloxScriptSecurity","Tags":["Yields"],"ThreadSafety":"Unsafe"}],"MemoryCategory":"Instances","Name":"PublishService","Superclass":"Instance","Tags":["NotCreatable","Service","NotReplicated"]},{"Members":[{"MemberType":"Function","Name":"AddGlobalPointsField","Parameters":[{"Name":"key","Type":{"Category":"Primitive","Name":"string"}},{"Name":"value","Type":{"Category":"Primitive","Name":"int"}}],"ReturnType":{"Category":"Primitive","Name":"void"},"Security":"RobloxScriptSecurity","ThreadSafety":"Unsafe"},{"MemberType":"Function","Name":"AddGlobalPointsTag","Parameters":[{"Name":"key","Type":{"Category":"Primitive","Name":"string"}},{"Name":"value","Type":{"Category":"Primitive","Name":"string"}}],"ReturnType":{"Category":"Primitive","Name":"void"},"Security":"RobloxScriptSecurity","ThreadSafety":"Unsafe"},{"MemberType":"Function","Name":"DEPRECATED_TrackEvent","Parameters":[{"Name":"category","Type":{"Category":"Primitive","Name":"string"}},{"Name":"action","Type":{"Category":"Primitive","Name":"string"}},{"Name":"label","Type":{"Category":"Primitive","Name":"string"}},{"Default":"0","Name":"value","Type":{"Category":"Primitive","Name":"int64"}}],"ReturnType":{"Category":"Primitive","Name":"void"},"Security":"RobloxScriptSecurity","ThreadSafety":"Unsafe"},{"MemberType":"Function","Name":"DEPRECATED_TrackEventWithArgs","Parameters":[{"Name":"category","Type":{"Category":"Primitive","Name":"string"}},{"Name":"action","Type":{"Category":"Primitive","Name":"string"}},{"Name":"label","Type":{"Category":"Primitive","Name":"string"}},{"Name":"args","Type":{"Category":"Group","Name":"Dictionary"}},{"Default":"0","Name":"value","Type":{"Category":"Primitive","Name":"int64"}}],"ReturnType":{"Category":"Primitive","Name":"void"},"Security":"RobloxScriptSecurity","ThreadSafety":"Unsafe"},{"MemberType":"Function","Name":"GetClientId","Parameters":[],"ReturnType":{"Category":"Primitive","Name":"string"},"Security":"RobloxScriptSecurity","ThreadSafety":"Unsafe"},{"MemberType":"Function","Name":"GetSessionId","Parameters":[],"ReturnType":{"Category":"Primitive","Name":"string"},"Security":"RobloxScriptSecurity","ThreadSafety":"Unsafe"},{"MemberType":"Function","Name":"ReleaseRBXEventStream","Parameters":[{"Name":"target","Type":{"Category":"Primitive","Name":"string"}}],"ReturnType":{"Category":"Primitive","Name":"void"},"Security":"RobloxScriptSecurity","ThreadSafety":"Unsafe"},{"MemberType":"Function","Name":"RemoveGlobalPointsField","Parameters":[{"Name":"key","Type":{"Category":"Primitive","Name":"string"}}],"ReturnType":{"Category":"Primitive","Name":"void"},"Security":"RobloxScriptSecurity","ThreadSafety":"Unsafe"},{"MemberType":"Function","Name":"RemoveGlobalPointsTag","Parameters":[{"Name":"key","Type":{"Category":"Primitive","Name":"string"}}],"ReturnType":{"Category":"Primitive","Name":"void"},"Security":"RobloxScriptSecurity","ThreadSafety":"Unsafe"},{"MemberType":"Function","Name":"ReportCounter","Parameters":[{"Name":"counterName","Type":{"Category":"Primitive","Name":"string"}},{"Default":"1","Name":"amount","Type":{"Category":"Primitive","Name":"int"}}],"ReturnType":{"Category":"Primitive","Name":"void"},"Security":"RobloxScriptSecurity","ThreadSafety":"Unsafe"},{"MemberType":"Function","Name":"ReportInfluxSeries","Parameters":[{"Name":"seriesName","Type":{"Category":"Primitive","Name":"string"}},{"Name":"points","Type":{"Category":"Group","Name":"Dictionary"}},{"Name":"throttlingPercentage","Type":{"Category":"Primitive","Name":"int"}}],"ReturnType":{"Category":"Primitive","Name":"void"},"Security":"RobloxScriptSecurity","ThreadSafety":"Unsafe"},{"MemberType":"Function","Name":"ReportStats","Parameters":[{"Name":"category","Type":{"Category":"Primitive","Name":"string"}},{"Name":"value","Type":{"Category":"Primitive","Name":"float"}}],"ReturnType":{"Category":"Primitive","Name":"void"},"Security":"RobloxScriptSecurity","ThreadSafety":"Unsafe"},{"MemberType":"Function","Name":"ReportToDiagByCountryCode","Parameters":[{"Name":"featureName","Type":{"Category":"Primitive","Name":"string"}},{"Name":"measureName","Type":{"Category":"Primitive","Name":"string"}},{"Name":"seconds","Type":{"Category":"Primitive","Name":"double"}}],"ReturnType":{"Category":"Primitive","Name":"void"},"Security":"RobloxScriptSecurity","ThreadSafety":"Unsafe"},{"MemberType":"Function","Name":"SendEventDeferred","Parameters":[{"Name":"target","Type":{"Category":"Primitive","Name":"string"}},{"Name":"eventContext","Type":{"Category":"Primitive","Name":"string"}},{"Name":"eventName","Type":{"Category":"Primitive","Name":"string"}},{"Name":"additionalArgs","Type":{"Category":"Group","Name":"Dictionary"}}],"ReturnType":{"Category":"Primitive","Name":"void"},"Security":"RobloxScriptSecurity","ThreadSafety":"Unsafe"},{"MemberType":"Function","Name":"SendEventImmediately","Parameters":[{"Name":"target","Type":{"Category":"Primitive","Name":"string"}},{"Name":"eventContext","Type":{"Category":"Primitive","Name":"string"}},{"Name":"eventName","Type":{"Category":"Primitive","Name":"string"}},{"Name":"additionalArgs","Type":{"Category":"Group","Name":"Dictionary"}}],"ReturnType":{"Category":"Primitive","Name":"void"},"Security":"RobloxScriptSecurity","ThreadSafety":"Unsafe"},{"MemberType":"Function","Name":"SetRBXEvent","Parameters":[{"Name":"target","Type":{"Category":"Primitive","Name":"string"}},{"Name":"eventContext","Type":{"Category":"Primitive","Name":"string"}},{"Name":"eventName","Type":{"Category":"Primitive","Name":"string"}},{"Name":"additionalArgs","Type":{"Category":"Group","Name":"Dictionary"}}],"ReturnType":{"Category":"Primitive","Name":"void"},"Security":"RobloxScriptSecurity","ThreadSafety":"Unsafe"},{"MemberType":"Function","Name":"SetRBXEventStream","Parameters":[{"Name":"target","Type":{"Category":"Primitive","Name":"string"}},{"Name":"eventContext","Type":{"Category":"Primitive","Name":"string"}},{"Name":"eventName","Type":{"Category":"Primitive","Name":"string"}},{"Name":"additionalArgs","Type":{"Category":"Group","Name":"Dictionary"}}],"ReturnType":{"Category":"Primitive","Name":"void"},"Security":"RobloxScriptSecurity","ThreadSafety":"Unsafe"},{"MemberType":"Function","Name":"TrackEvent","Parameters":[{"Name":"category","Type":{"Category":"Primitive","Name":"string"}},{"Name":"action","Type":{"Category":"Primitive","Name":"string"}},{"Name":"label","Type":{"Category":"Primitive","Name":"string"}},{"Default":"0","Name":"value","Type":{"Category":"Primitive","Name":"int64"}}],"ReturnType":{"Category":"Primitive","Name":"void"},"Security":"RobloxScriptSecurity","ThreadSafety":"Unsafe"},{"MemberType":"Function","Name":"TrackEventWithArgs","Parameters":[{"Name":"category","Type":{"Category":"Primitive","Name":"string"}},{"Name":"action","Type":{"Category":"Primitive","Name":"string"}},{"Name":"label","Type":{"Category":"Primitive","Name":"string"}},{"Name":"args","Type":{"Category":"Group","Name":"Dictionary"}},{"Default":"0","Name":"value","Type":{"Category":"Primitive","Name":"int64"}}],"ReturnType":{"Category":"Primitive","Name":"void"},"Security":"RobloxScriptSecurity","ThreadSafety":"Unsafe"},{"MemberType":"Function","Name":"UpdateHeartbeatObject","Parameters":[{"Name":"args","Type":{"Category":"Group","Name":"Dictionary"}}],"ReturnType":{"Category":"Primitive","Name":"void"},"Security":"RobloxScriptSecurity","ThreadSafety":"Unsafe"}],"MemoryCategory":"Instances","Name":"RbxAnalyticsService","Superclass":"Instance","Tags":["NotCreatable","Service"]},{"Members":[],"MemoryCategory":"Instances","Name":"ReflectionMetadata","Superclass":"Instance"},{"Members":[],"MemoryCategory":"Instances","Name":"ReflectionMetadataCallbacks","Superclass":"Instance"},{"Members":[],"MemoryCategory":"Instances","Name":"ReflectionMetadataClasses","Superclass":"Instance"},{"Members":[],"MemoryCategory":"Instances","Name":"ReflectionMetadataEnums","Superclass":"Instance"},{"Members":[],"MemoryCategory":"Instances","Name":"ReflectionMetadataEvents","Superclass":"Instance"},{"Members":[],"MemoryCategory":"Instances","Name":"ReflectionMetadataFunctions","Superclass":"Instance"},{"Members":[{"Category":"Reflection","MemberType":"Property","Name":"Browsable","Security":{"Read":"None","Write":"None"},"Serialization":{"CanLoad":true,"CanSave":true},"ThreadSafety":"ReadSafe","ValueType":{"Category":"Primitive","Name":"bool"}},{"Category":"Reflection","MemberType":"Property","Name":"ClassCategory","Security":{"Read":"None","Write":"None"},"Serialization":{"CanLoad":true,"CanSave":true},"ThreadSafety":"ReadSafe","ValueType":{"Category":"Primitive","Name":"string"}},{"Category":"Reflection","MemberType":"Property","Name":"ClientOnly","Security":{"Read":"None","Write":"None"},"Serialization":{"CanLoad":true,"CanSave":true},"ThreadSafety":"ReadSafe","ValueType":{"Category":"Primitive","Name":"bool"}},{"Category":"Reflection","MemberType":"Property","Name":"Constraint","Security":{"Read":"None","Write":"None"},"Serialization":{"CanLoad":true,"CanSave":true},"ThreadSafety":"ReadSafe","ValueType":{"Category":"Primitive","Name":"string"}},{"Category":"Reflection","MemberType":"Property","Name":"Deprecated","Security":{"Read":"None","Write":"None"},"Serialization":{"CanLoad":true,"CanSave":true},"ThreadSafety":"ReadSafe","ValueType":{"Category":"Primitive","Name":"bool"}},{"Category":"Reflection","MemberType":"Property","Name":"EditingDisabled","Security":{"Read":"None","Write":"None"},"Serialization":{"CanLoad":true,"CanSave":true},"ThreadSafety":"ReadSafe","ValueType":{"Category":"Primitive","Name":"bool"}},{"Category":"Reflection","MemberType":"Property","Name":"EditorType","Security":{"Read":"None","Write":"None"},"Serialization":{"CanLoad":true,"CanSave":true},"ThreadSafety":"ReadSafe","ValueType":{"Category":"Primitive","Name":"string"}},{"Category":"Reflection","MemberType":"Property","Name":"FFlag","Security":{"Read":"None","Write":"None"},"Serialization":{"CanLoad":true,"CanSave":true},"ThreadSafety":"ReadSafe","ValueType":{"Category":"Primitive","Name":"string"}},{"Category":"Reflection","MemberType":"Property","Name":"IsBackend","Security":{"Read":"None","Write":"None"},"Serialization":{"CanLoad":true,"CanSave":true},"ThreadSafety":"ReadSafe","ValueType":{"Category":"Primitive","Name":"bool"}},{"Category":"Reflection","MemberType":"Property","Name":"PropertyOrder","Security":{"Read":"None","Write":"None"},"Serialization":{"CanLoad":true,"CanSave":true},"ThreadSafety":"ReadSafe","ValueType":{"Category":"Primitive","Name":"int"}},{"Category":"Reflection","MemberType":"Property","Name":"ScriptContext","Security":{"Read":"None","Write":"None"},"Serialization":{"CanLoad":true,"CanSave":true},"ThreadSafety":"ReadSafe","ValueType":{"Category":"Primitive","Name":"string"}},{"Category":"Reflection","MemberType":"Property","Name":"ServerOnly","Security":{"Read":"None","Write":"None"},"Serialization":{"CanLoad":true,"CanSave":true},"ThreadSafety":"ReadSafe","ValueType":{"Category":"Primitive","Name":"bool"}},{"Category":"Reflection","MemberType":"Property","Name":"SliderScaling","Security":{"Read":"None","Write":"None"},"Serialization":{"CanLoad":true,"CanSave":true},"ThreadSafety":"ReadSafe","ValueType":{"Category":"Primitive","Name":"string"}},{"Category":"Reflection","MemberType":"Property","Name":"UIMaximum","Security":{"Read":"None","Write":"None"},"Serialization":{"CanLoad":true,"CanSave":true},"ThreadSafety":"ReadSafe","ValueType":{"Category":"Primitive","Name":"double"}},{"Category":"Reflection","MemberType":"Property","Name":"UIMinimum","Security":{"Read":"None","Write":"None"},"Serialization":{"CanLoad":true,"CanSave":true},"ThreadSafety":"ReadSafe","ValueType":{"Category":"Primitive","Name":"double"}},{"Category":"Reflection","MemberType":"Property","Name":"UINumTicks","Security":{"Read":"None","Write":"None"},"Serialization":{"CanLoad":true,"CanSave":true},"ThreadSafety":"ReadSafe","ValueType":{"Category":"Primitive","Name":"double"}}],"MemoryCategory":"Instances","Name":"ReflectionMetadataItem","Superclass":"Instance","Tags":["NotCreatable"]},{"Members":[{"Category":"Reflection","MemberType":"Property","Name":"ExplorerImageIndex","Security":{"Read":"None","Write":"None"},"Serialization":{"CanLoad":true,"CanSave":true},"ThreadSafety":"ReadSafe","ValueType":{"Category":"Primitive","Name":"int"}},{"Category":"Reflection","MemberType":"Property","Name":"ExplorerOrder","Security":{"Read":"None","Write":"None"},"Serialization":{"CanLoad":true,"CanSave":true},"ThreadSafety":"ReadSafe","ValueType":{"Category":"Primitive","Name":"int"}},{"Category":"Reflection","MemberType":"Property","Name":"Insertable","Security":{"Read":"None","Write":"None"},"Serialization":{"CanLoad":true,"CanSave":true},"ThreadSafety":"ReadSafe","ValueType":{"Category":"Primitive","Name":"bool"}},{"Category":"Reflection","MemberType":"Property","Name":"PreferredParent","Security":{"Read":"None","Write":"None"},"Serialization":{"CanLoad":true,"CanSave":true},"ThreadSafety":"ReadSafe","ValueType":{"Category":"Primitive","Name":"string"}}],"MemoryCategory":"Instances","Name":"ReflectionMetadataClass","Superclass":"ReflectionMetadataItem"},{"Members":[],"MemoryCategory":"Instances","Name":"ReflectionMetadataEnum","Superclass":"ReflectionMetadataItem"},{"Members":[],"MemoryCategory":"Instances","Name":"ReflectionMetadataEnumItem","Superclass":"ReflectionMetadataItem"},{"Members":[],"MemoryCategory":"Instances","Name":"ReflectionMetadataMember","Superclass":"ReflectionMetadataItem"},{"Members":[],"MemoryCategory":"Instances","Name":"ReflectionMetadataProperties","Superclass":"Instance"},{"Members":[],"MemoryCategory":"Instances","Name":"ReflectionMetadataYieldFunctions","Superclass":"Instance"},{"Members":[],"MemoryCategory":"Instances","Name":"RemoteDebuggerServer","Superclass":"Instance","Tags":["NotCreatable","Service","NotReplicated"]},{"Members":[{"MemberType":"Function","Name":"FireAllClients","Parameters":[{"Name":"arguments","Type":{"Category":"Group","Name":"Tuple"}}],"ReturnType":{"Category":"Primitive","Name":"void"},"Security":"None","ThreadSafety":"Unsafe"},{"MemberType":"Function","Name":"FireClient","Parameters":[{"Name":"player","Type":{"Category":"Class","Name":"Player"}},{"Name":"arguments","Type":{"Category":"Group","Name":"Tuple"}}],"ReturnType":{"Category":"Primitive","Name":"void"},"Security":"None","ThreadSafety":"Unsafe"},{"MemberType":"Function","Name":"FireServer","Parameters":[{"Name":"arguments","Type":{"Category":"Group","Name":"Tuple"}}],"ReturnType":{"Category":"Primitive","Name":"void"},"Security":"None","ThreadSafety":"Unsafe"},{"MemberType":"Event","Name":"OnClientEvent","Parameters":[{"Name":"arguments","Type":{"Category":"Group","Name":"Tuple"}}],"Security":"None","ThreadSafety":"Unsafe"},{"MemberType":"Event","Name":"OnServerEvent","Parameters":[{"Name":"player","Type":{"Category":"Class","Name":"Player"}},{"Name":"arguments","Type":{"Category":"Group","Name":"Tuple"}}],"Security":"None","ThreadSafety":"Unsafe"}],"MemoryCategory":"Instances","Name":"RemoteEvent","Superclass":"Instance"},{"Members":[{"MemberType":"Function","Name":"InvokeClient","Parameters":[{"Name":"player","Type":{"Category":"Class","Name":"Player"}},{"Name":"arguments","Type":{"Category":"Group","Name":"Tuple"}}],"ReturnType":{"Category":"Group","Name":"Tuple"},"Security":"None","Tags":["Yields"],"ThreadSafety":"Unsafe"},{"MemberType":"Function","Name":"InvokeServer","Parameters":[{"Name":"arguments","Type":{"Category":"Group","Name":"Tuple"}}],"ReturnType":{"Category":"Group","Name":"Tuple"},"Security":"None","Tags":["Yields"],"ThreadSafety":"Unsafe"},{"MemberType":"Callback","Name":"OnClientInvoke","Parameters":[{"Name":"arguments","Type":{"Category":"Group","Name":"Tuple"}}],"ReturnType":{"Category":"Group","Name":"Tuple"},"Security":"None","ThreadSafety":"Unsafe"},{"MemberType":"Callback","Name":"OnServerInvoke","Parameters":[{"Name":"player","Type":{"Category":"Class","Name":"Player"}},{"Name":"arguments","Type":{"Category":"Group","Name":"Tuple"}}],"ReturnType":{"Category":"Group","Name":"Tuple"},"Security":"None","ThreadSafety":"Unsafe"}],"MemoryCategory":"Instances","Name":"RemoteFunction","Superclass":"Instance"},{"Members":[{"Category":"Debug","MemberType":"Property","Name":"AutoFRMLevel","Security":{"Read":"None","Write":"None"},"Serialization":{"CanLoad":true,"CanSave":true},"ThreadSafety":"ReadSafe","ValueType":{"Category":"Primitive","Name":"int"}},{"Category":"Performance","MemberType":"Property","Name":"EagerBulkExecution","Security":{"Read":"None","Write":"None"},"Serialization":{"CanLoad":true,"CanSave":true},"ThreadSafety":"ReadSafe","ValueType":{"Category":"Primitive","Name":"bool"}},{"Category":"Performance","MemberType":"Property","Name":"EditQualityLevel","Security":{"Read":"None","Write":"None"},"Serialization":{"CanLoad":true,"CanSave":true},"ThreadSafety":"ReadSafe","ValueType":{"Category":"Enum","Name":"QualityLevel"}},{"Category":"Debug","MemberType":"Property","Name":"EnableFRM","Security":{"Read":"None","Write":"None"},"Serialization":{"CanLoad":true,"CanSave":false},"Tags":["Hidden","NotReplicated"],"ThreadSafety":"ReadSafe","ValueType":{"Category":"Primitive","Name":"bool"}},{"Category":"General","MemberType":"Property","Name":"ExportMergeByMaterial","Security":{"Read":"None","Write":"None"},"Serialization":{"CanLoad":true,"CanSave":true},"ThreadSafety":"ReadSafe","ValueType":{"Category":"Primitive","Name":"bool"}},{"Category":"General","MemberType":"Property","Name":"FrameRateManager","Security":{"Read":"None","Write":"None"},"Serialization":{"CanLoad":true,"CanSave":true},"ThreadSafety":"ReadSafe","ValueType":{"Category":"Enum","Name":"FramerateManagerMode"}},{"Category":"General","MemberType":"Property","Name":"GraphicsMode","Security":{"Read":"None","Write":"None"},"Serialization":{"CanLoad":true,"CanSave":true},"ThreadSafety":"ReadSafe","ValueType":{"Category":"Enum","Name":"GraphicsMode"}},{"Category":"Cache","MemberType":"Property","Name":"MeshCacheSize","Security":{"Read":"None","Write":"None"},"Serialization":{"CanLoad":true,"CanSave":true},"ThreadSafety":"ReadSafe","ValueType":{"Category":"Primitive","Name":"int"}},{"Category":"Debug","MemberType":"Property","Name":"MeshPartDetailLevel","Security":{"Read":"None","Write":"None"},"Serialization":{"CanLoad":true,"CanSave":true},"ThreadSafety":"ReadSafe","ValueType":{"Category":"Enum","Name":"MeshPartDetailLevel"}},{"Category":"Performance","MemberType":"Property","Name":"QualityLevel","Security":{"Read":"None","Write":"None"},"Serialization":{"CanLoad":true,"CanSave":true},"ThreadSafety":"ReadSafe","ValueType":{"Category":"Enum","Name":"QualityLevel"}},{"Category":"Debug","MemberType":"Property","Name":"ReloadAssets","Security":{"Read":"None","Write":"None"},"Serialization":{"CanLoad":true,"CanSave":true},"ThreadSafety":"ReadSafe","ValueType":{"Category":"Primitive","Name":"bool"}},{"Category":"Debug","MemberType":"Property","Name":"RenderCSGTrianglesDebug","Security":{"Read":"None","Write":"None"},"Serialization":{"CanLoad":true,"CanSave":true},"ThreadSafety":"ReadSafe","ValueType":{"Category":"Primitive","Name":"bool"}},{"Category":"Debug","MemberType":"Property","Name":"ShowBoundingBoxes","Security":{"Read":"None","Write":"None"},"Serialization":{"CanLoad":true,"CanSave":true},"ThreadSafety":"ReadSafe","ValueType":{"Category":"Primitive","Name":"bool"}},{"MemberType":"Function","Name":"GetMaxQualityLevel","Parameters":[],"ReturnType":{"Category":"Primitive","Name":"int"},"Security":"None","ThreadSafety":"Unsafe"}],"MemoryCategory":"Instances","Name":"RenderSettings","Superclass":"Instance","Tags":["NotCreatable","Service","NotBrowsable"]},{"Members":[{"Category":"RenderingTest","MemberType":"Property","Name":"CFrame","Security":{"Read":"None","Write":"None"},"Serialization":{"CanLoad":true,"CanSave":true},"ThreadSafety":"ReadSafe","ValueType":{"Category":"DataType","Name":"CFrame"}},{"Category":"RenderingTest","MemberType":"Property","Name":"ComparisonDiffThreshold","Security":{"Read":"None","Write":"None"},"Serialization":{"CanLoad":true,"CanSave":true},"ThreadSafety":"ReadSafe","ValueType":{"Category":"Primitive","Name":"int"}},{"Category":"RenderingTest","MemberType":"Property","Name":"ComparisonMethod","Security":{"Read":"None","Write":"None"},"Serialization":{"CanLoad":true,"CanSave":true},"ThreadSafety":"ReadSafe","ValueType":{"Category":"Enum","Name":"RenderingTestComparisonMethod"}},{"Category":"RenderingTest","MemberType":"Property","Name":"ComparisonPsnrThreshold","Security":{"Read":"None","Write":"None"},"Serialization":{"CanLoad":true,"CanSave":true},"ThreadSafety":"ReadSafe","ValueType":{"Category":"Primitive","Name":"float"}},{"Category":"RenderingTest","MemberType":"Property","Name":"Description","Security":{"Read":"None","Write":"None"},"Serialization":{"CanLoad":true,"CanSave":true},"ThreadSafety":"ReadSafe","ValueType":{"Category":"Primitive","Name":"string"}},{"Category":"RenderingTest","MemberType":"Property","Name":"FieldOfView","Security":{"Read":"None","Write":"None"},"Serialization":{"CanLoad":true,"CanSave":true},"ThreadSafety":"ReadSafe","ValueType":{"Category":"Primitive","Name":"float"}},{"Category":"RenderingTest","MemberType":"Property","Name":"Orientation","Security":{"Read":"None","Write":"None"},"Serialization":{"CanLoad":false,"CanSave":false},"Tags":["Hidden","NotReplicated"],"ThreadSafety":"ReadSafe","ValueType":{"Category":"DataType","Name":"Vector3"}},{"Category":"RenderingTest","MemberType":"Property","Name":"Position","Security":{"Read":"None","Write":"None"},"Serialization":{"CanLoad":false,"CanSave":false},"Tags":["Hidden","NotReplicated"],"ThreadSafety":"ReadSafe","ValueType":{"Category":"DataType","Name":"Vector3"}},{"Category":"RenderingTest","MemberType":"Property","Name":"QualityLevel","Security":{"Read":"None","Write":"None"},"Serialization":{"CanLoad":true,"CanSave":true},"ThreadSafety":"ReadSafe","ValueType":{"Category":"Primitive","Name":"int"}},{"Category":"RenderingTest","MemberType":"Property","Name":"ShouldSkip","Security":{"Read":"None","Write":"None"},"Serialization":{"CanLoad":true,"CanSave":true},"ThreadSafety":"ReadSafe","ValueType":{"Category":"Primitive","Name":"bool"}},{"Category":"RenderingTest","MemberType":"Property","Name":"Ticket","Security":{"Read":"None","Write":"None"},"Serialization":{"CanLoad":true,"CanSave":true},"ThreadSafety":"ReadSafe","ValueType":{"Category":"Primitive","Name":"string"}},{"MemberType":"Function","Name":"RenderdocTriggerCapture","Parameters":[],"ReturnType":{"Category":"Primitive","Name":"void"},"Security":"None","ThreadSafety":"Unsafe"}],"MemoryCategory":"Instances","Name":"RenderingTest","Superclass":"Instance"},{"Members":[{"MemberType":"Function","Name":"IsDefaultLoadingGuiRemoved","Parameters":[],"ReturnType":{"Category":"Primitive","Name":"bool"},"Security":"RobloxScriptSecurity","ThreadSafety":"Unsafe"},{"MemberType":"Function","Name":"IsFinishedReplicating","Parameters":[],"ReturnType":{"Category":"Primitive","Name":"bool"},"Security":"RobloxScriptSecurity","ThreadSafety":"Unsafe"},{"MemberType":"Function","Name":"RemoveDefaultLoadingScreen","Parameters":[],"ReturnType":{"Category":"Primitive","Name":"void"},"Security":"None","ThreadSafety":"Unsafe"},{"MemberType":"Function","Name":"SetDefaultLoadingGuiRemoved","Parameters":[],"ReturnType":{"Category":"Primitive","Name":"void"},"Security":"RobloxScriptSecurity","ThreadSafety":"Unsafe"},{"MemberType":"Event","Name":"DefaultLoadingGuiRemoved","Parameters":[],"Security":"RobloxScriptSecurity","ThreadSafety":"Unsafe"},{"MemberType":"Event","Name":"FinishedReplicating","Parameters":[],"Security":"RobloxScriptSecurity","ThreadSafety":"Unsafe"},{"MemberType":"Event","Name":"RemoveDefaultLoadingGuiSignal","Parameters":[],"Security":"RobloxScriptSecurity","ThreadSafety":"Unsafe"}],"MemoryCategory":"Instances","Name":"ReplicatedFirst","Superclass":"Instance","Tags":["NotCreatable","Service"]},{"Members":[],"MemoryCategory":"Instances","Name":"ReplicatedStorage","Superclass":"Instance","Tags":["NotCreatable","Service"]},{"Members":[],"MemoryCategory":"Instances","Name":"RobloxPluginGuiService","Superclass":"Instance","Tags":["NotCreatable","Service","NotReplicated"]},{"Members":[],"MemoryCategory":"Instances","Name":"RobloxReplicatedStorage","Superclass":"Instance","Tags":["NotCreatable","Service","NotBrowsable"]},{"Members":[{"Category":"Data","MemberType":"Property","Name":"Length","Security":{"Read":"None","Write":"None"},"Serialization":{"CanLoad":false,"CanSave":true},"Tags":["ReadOnly","NotReplicated"],"ThreadSafety":"ReadSafe","ValueType":{"Category":"Primitive","Name":"int"}},{"MemberType":"Function","Name":"GetKeyAtIndex","Parameters":[{"Name":"index","Type":{"Category":"Primitive","Name":"int"}}],"ReturnType":{"Category":"DataType","Name":"RotationCurveKey"},"Security":"None","ThreadSafety":"Unsafe"},{"MemberType":"Function","Name":"GetKeyIndicesAtTime","Parameters":[{"Name":"time","Type":{"Category":"Primitive","Name":"float"}}],"ReturnType":{"Category":"Group","Name":"Array"},"Security":"None","ThreadSafety":"Unsafe"},{"MemberType":"Function","Name":"GetKeys","Parameters":[],"ReturnType":{"Category":"Group","Name":"Array"},"Security":"None","ThreadSafety":"Unsafe"},{"MemberType":"Function","Name":"GetValueAtTime","Parameters":[{"Name":"time","Type":{"Category":"Primitive","Name":"float"}}],"ReturnType":{"Category":"DataType","Name":"CoordinateFrame?"},"Security":"None","ThreadSafety":"Unsafe"},{"MemberType":"Function","Name":"InsertKey","Parameters":[{"Name":"key","Type":{"Category":"DataType","Name":"RotationCurveKey"}}],"ReturnType":{"Category":"Group","Name":"Array"},"Security":"None","ThreadSafety":"Unsafe"},{"MemberType":"Function","Name":"RemoveKeyAtIndex","Parameters":[{"Name":"startingIndex","Type":{"Category":"Primitive","Name":"int"}},{"Default":"1","Name":"count","Type":{"Category":"Primitive","Name":"int"}}],"ReturnType":{"Category":"Primitive","Name":"int"},"Security":"None","ThreadSafety":"Unsafe"},{"MemberType":"Function","Name":"SetKeys","Parameters":[{"Name":"keys","Type":{"Category":"Group","Name":"Array"}}],"ReturnType":{"Category":"Primitive","Name":"int"},"Security":"None","ThreadSafety":"Unsafe"}],"MemoryCategory":"Instances","Name":"RotationCurve","Superclass":"Instance"},{"Members":[],"MemoryCategory":"Instances","Name":"RtMessagingService","Superclass":"Instance","Tags":["NotCreatable","Service","NotReplicated"]},{"Members":[{"Category":"Data","MemberType":"Property","Name":"ClientGitHash","Security":{"Read":"RobloxScriptSecurity","Write":"RobloxScriptSecurity"},"Serialization":{"CanLoad":false,"CanSave":false},"Tags":["ReadOnly","NotReplicated"],"ThreadSafety":"ReadSafe","ValueType":{"Category":"Primitive","Name":"string"}},{"MemberType":"Function","Name":"BindToRenderStep","Parameters":[{"Name":"name","Type":{"Category":"Primitive","Name":"string"}},{"Name":"priority","Type":{"Category":"Primitive","Name":"int"}},{"Name":"function","Type":{"Category":"DataType","Name":"Function"}}],"ReturnType":{"Category":"Primitive","Name":"void"},"Security":"None","ThreadSafety":"Unsafe"},{"MemberType":"Function","Name":"GetCoreScriptVersion","Parameters":[],"ReturnType":{"Category":"Primitive","Name":"string"},"Security":"RobloxScriptSecurity","ThreadSafety":"Unsafe"},{"MemberType":"Function","Name":"GetRobloxClientChannel","Parameters":[],"ReturnType":{"Category":"Primitive","Name":"string"},"Security":"RobloxScriptSecurity","ThreadSafety":"Unsafe"},{"MemberType":"Function","Name":"GetRobloxVersion","Parameters":[],"ReturnType":{"Category":"Primitive","Name":"string"},"Security":"RobloxScriptSecurity","ThreadSafety":"Unsafe"},{"MemberType":"Function","Name":"IsClient","Parameters":[],"ReturnType":{"Category":"Primitive","Name":"bool"},"Security":"None","ThreadSafety":"Safe"},{"MemberType":"Function","Name":"IsEdit","Parameters":[],"ReturnType":{"Category":"Primitive","Name":"bool"},"Security":"PluginSecurity","ThreadSafety":"Safe"},{"MemberType":"Function","Name":"IsRunMode","Parameters":[],"ReturnType":{"Category":"Primitive","Name":"bool"},"Security":"None","ThreadSafety":"Safe"},{"MemberType":"Function","Name":"IsRunning","Parameters":[],"ReturnType":{"Category":"Primitive","Name":"bool"},"Security":"None","ThreadSafety":"Unsafe"},{"MemberType":"Function","Name":"IsServer","Parameters":[],"ReturnType":{"Category":"Primitive","Name":"bool"},"Security":"None","ThreadSafety":"Safe"},{"MemberType":"Function","Name":"IsStudio","Parameters":[],"ReturnType":{"Category":"Primitive","Name":"bool"},"Security":"None","ThreadSafety":"Safe"},{"MemberType":"Function","Name":"Pause","Parameters":[],"ReturnType":{"Category":"Primitive","Name":"void"},"Security":"PluginSecurity","ThreadSafety":"Unsafe"},{"MemberType":"Function","Name":"Reset","Parameters":[],"ReturnType":{"Category":"Primitive","Name":"void"},"Security":"PluginSecurity","Tags":["Deprecated"],"ThreadSafety":"Unsafe"},{"MemberType":"Function","Name":"Run","Parameters":[],"ReturnType":{"Category":"Primitive","Name":"void"},"Security":"PluginSecurity","ThreadSafety":"Unsafe"},{"MemberType":"Function","Name":"Set3dRenderingEnabled","Parameters":[{"Name":"enable","Type":{"Category":"Primitive","Name":"bool"}}],"ReturnType":{"Category":"Primitive","Name":"void"},"Security":"RobloxScriptSecurity","ThreadSafety":"Unsafe"},{"MemberType":"Function","Name":"SetRobloxGuiFocused","Parameters":[{"Name":"focus","Type":{"Category":"Primitive","Name":"bool"}}],"ReturnType":{"Category":"Primitive","Name":"void"},"Security":"RobloxScriptSecurity","ThreadSafety":"Unsafe"},{"MemberType":"Function","Name":"Stop","Parameters":[],"ReturnType":{"Category":"Primitive","Name":"void"},"Security":"PluginSecurity","ThreadSafety":"Unsafe"},{"MemberType":"Function","Name":"UnbindFromRenderStep","Parameters":[{"Name":"name","Type":{"Category":"Primitive","Name":"string"}}],"ReturnType":{"Category":"Primitive","Name":"void"},"Security":"None","ThreadSafety":"Unsafe"},{"MemberType":"Function","Name":"setThrottleFramerateEnabled","Parameters":[{"Name":"enable","Type":{"Category":"Primitive","Name":"bool"}}],"ReturnType":{"Category":"Primitive","Name":"void"},"Security":"RobloxScriptSecurity","ThreadSafety":"Unsafe"},{"MemberType":"Event","Name":"Heartbeat","Parameters":[{"Name":"deltaTime","Type":{"Category":"Primitive","Name":"double"}}],"Security":"None","ThreadSafety":"Unsafe"},{"MemberType":"Event","Name":"PostSimulation","Parameters":[{"Name":"deltaTimeSim","Type":{"Category":"Primitive","Name":"double"}}],"Security":"None","ThreadSafety":"Unsafe"},{"MemberType":"Event","Name":"PreAnimation","Parameters":[{"Name":"deltaTimeSim","Type":{"Category":"Primitive","Name":"double"}}],"Security":"None","ThreadSafety":"Unsafe"},{"MemberType":"Event","Name":"PreRender","Parameters":[{"Name":"deltaTimeRender","Type":{"Category":"Primitive","Name":"double"}}],"Security":"None","ThreadSafety":"Unsafe"},{"MemberType":"Event","Name":"PreSimulation","Parameters":[{"Name":"deltaTimeSim","Type":{"Category":"Primitive","Name":"double"}}],"Security":"None","ThreadSafety":"Unsafe"},{"MemberType":"Event","Name":"RenderStepped","Parameters":[{"Name":"deltaTime","Type":{"Category":"Primitive","Name":"double"}}],"Security":"None","ThreadSafety":"Unsafe"},{"MemberType":"Event","Name":"Stepped","Parameters":[{"Name":"time","Type":{"Category":"Primitive","Name":"double"}},{"Name":"deltaTime","Type":{"Category":"Primitive","Name":"double"}}],"Security":"None","ThreadSafety":"Unsafe"}],"MemoryCategory":"Instances","Name":"RunService","Superclass":"Instance","Tags":["NotCreatable","Service","NotReplicated"]},{"Members":[],"MemoryCategory":"Instances","Name":"RuntimeScriptService","Superclass":"Instance","Tags":["NotCreatable","Service","NotReplicated"]},{"Members":[{"Category":"Appearance","MemberType":"Property","Name":"CameraButtonIcon","Security":{"Read":"None","Write":"None"},"Serialization":{"CanLoad":true,"CanSave":true},"ThreadSafety":"ReadSafe","ValueType":{"Category":"DataType","Name":"Content"}},{"Category":"Appearance","MemberType":"Property","Name":"CameraButtonPosition","Security":{"Read":"None","Write":"None"},"Serialization":{"CanLoad":true,"CanSave":true},"ThreadSafety":"ReadSafe","ValueType":{"Category":"DataType","Name":"UDim2"}},{"Category":"Appearance","MemberType":"Property","Name":"CloseButtonPosition","Security":{"Read":"None","Write":"None"},"Serialization":{"CanLoad":true,"CanSave":true},"ThreadSafety":"ReadSafe","ValueType":{"Category":"DataType","Name":"UDim2"}},{"Category":"Data","MemberType":"Property","Name":"CloseWhenScreenshotTaken","Security":{"Read":"None","Write":"None"},"Serialization":{"CanLoad":true,"CanSave":true},"ThreadSafety":"ReadSafe","ValueType":{"Category":"Primitive","Name":"bool"}},{"Category":"Appearance","MemberType":"Property","Name":"ExperienceNameOverlayEnabled","Security":{"Read":"None","Write":"None"},"Serialization":{"CanLoad":true,"CanSave":true},"ThreadSafety":"ReadSafe","ValueType":{"Category":"Primitive","Name":"bool"}},{"Category":"Appearance","MemberType":"Property","Name":"OverlayFont","Security":{"Read":"None","Write":"None"},"Serialization":{"CanLoad":true,"CanSave":true},"ThreadSafety":"ReadSafe","ValueType":{"Category":"Enum","Name":"Font"}},{"Category":"Appearance","MemberType":"Property","Name":"UsernameOverlayEnabled","Security":{"Read":"None","Write":"None"},"Serialization":{"CanLoad":true,"CanSave":true},"ThreadSafety":"ReadSafe","ValueType":{"Category":"Primitive","Name":"bool"}},{"Category":"State","MemberType":"Property","Name":"Visible","Security":{"Read":"None","Write":"None"},"Serialization":{"CanLoad":true,"CanSave":true},"ThreadSafety":"ReadSafe","ValueType":{"Category":"Primitive","Name":"bool"}}],"MemoryCategory":"Instances","Name":"ScreenshotHud","Superclass":"Instance","Tags":["NotCreatable","NotReplicated"]},{"Members":[],"MemoryCategory":"Instances","Name":"ScriptBuilder","Superclass":"Instance","Tags":["NotCreatable","NotReplicated"]},{"Members":[],"MemoryCategory":"Instances","Name":"CoreScriptBuilder","Superclass":"ScriptBuilder","Tags":["NotCreatable","NotReplicated"]},{"Members":[{"MemberType":"Event","Name":"ScriptAdded","Parameters":[{"Name":"script","Type":{"Category":"Class","Name":"LuaSourceContainer"}}],"Security":"RobloxScriptSecurity","ThreadSafety":"Unsafe"},{"MemberType":"Event","Name":"ScriptBeingRemoved","Parameters":[{"Name":"script","Type":{"Category":"Class","Name":"LuaSourceContainer"}}],"Security":"RobloxScriptSecurity","ThreadSafety":"Unsafe"},{"MemberType":"Event","Name":"ScriptChanged","Parameters":[{"Name":"script","Type":{"Category":"Class","Name":"LuaSourceContainer"}},{"Name":"property","Type":{"Category":"Primitive","Name":"string"}}],"Security":"RobloxScriptSecurity","ThreadSafety":"Unsafe"},{"MemberType":"Event","Name":"ScriptFullNameChanged","Parameters":[{"Name":"script","Type":{"Category":"Class","Name":"LuaSourceContainer"}}],"Security":"RobloxScriptSecurity","ThreadSafety":"Unsafe"},{"MemberType":"Event","Name":"ScriptSourceChanged","Parameters":[{"Name":"script","Type":{"Category":"Class","Name":"LuaSourceContainer"}}],"Security":"RobloxScriptSecurity","ThreadSafety":"Unsafe"}],"MemoryCategory":"Instances","Name":"ScriptChangeService","Superclass":"Instance","Tags":["NotCreatable","Service","NotReplicated"]},{"Members":[],"MemoryCategory":"Instances","Name":"ScriptCloneWatcher","Superclass":"Instance","Tags":["NotCreatable","Service","NotReplicated"]},{"Members":[],"MemoryCategory":"Instances","Name":"ScriptCloneWatcherHelper","Superclass":"Instance","Tags":["NotCreatable","Service","NotReplicated"]},{"Members":[{"Category":"State","MemberType":"Property","Name":"ScriptsDisabled","Security":{"Read":"LocalUserSecurity","Write":"LocalUserSecurity"},"Serialization":{"CanLoad":false,"CanSave":false},"Tags":["Hidden"],"ThreadSafety":"ReadSafe","ValueType":{"Category":"Primitive","Name":"bool"}},{"MemberType":"Function","Name":"AddCoreScriptLocal","Parameters":[{"Name":"name","Type":{"Category":"Primitive","Name":"string"}},{"Name":"parent","Type":{"Category":"Class","Name":"Instance"}}],"ReturnType":{"Category":"Primitive","Name":"void"},"Security":"RobloxScriptSecurity","ThreadSafety":"Unsafe"},{"MemberType":"Function","Name":"ClearScriptProfilingData","Parameters":[],"ReturnType":{"Category":"Primitive","Name":"void"},"Security":"RobloxScriptSecurity","ThreadSafety":"Unsafe"},{"MemberType":"Function","Name":"DeserializeScriptProfilerString","Parameters":[{"Name":"jsonString","Type":{"Category":"Primitive","Name":"string"}}],"ReturnType":{"Category":"Group","Name":"Dictionary"},"Security":"RobloxScriptSecurity","Tags":["CustomLuaState"],"ThreadSafety":"Unsafe"},{"MemberType":"Function","Name":"GetCoverageStats","Parameters":[],"ReturnType":{"Category":"Group","Name":"Array"},"Security":"RobloxScriptSecurity","ThreadSafety":"Unsafe"},{"MemberType":"Function","Name":"SaveScriptProfilingData","Parameters":[{"Name":"filename","Type":{"Category":"Primitive","Name":"string"}}],"ReturnType":{"Category":"Primitive","Name":"void"},"Security":"RobloxScriptSecurity","ThreadSafety":"Unsafe"},{"MemberType":"Function","Name":"SetTimeout","Parameters":[{"Name":"seconds","Type":{"Category":"Primitive","Name":"double"}}],"ReturnType":{"Category":"Primitive","Name":"void"},"Security":"PluginSecurity","ThreadSafety":"Unsafe"},{"MemberType":"Function","Name":"StartScriptProfiling","Parameters":[],"ReturnType":{"Category":"Primitive","Name":"void"},"Security":"RobloxScriptSecurity","ThreadSafety":"Unsafe"},{"MemberType":"Function","Name":"StopScriptProfiling","Parameters":[],"ReturnType":{"Category":"Group","Name":"Dictionary"},"Security":"RobloxScriptSecurity","Tags":["CustomLuaState"],"ThreadSafety":"Unsafe"},{"MemberType":"Event","Name":"Error","Parameters":[{"Name":"message","Type":{"Category":"Primitive","Name":"string"}},{"Name":"stackTrace","Type":{"Category":"Primitive","Name":"string"}},{"Name":"script","Type":{"Category":"Class","Name":"Instance"}}],"Security":"None","ThreadSafety":"Unsafe"},{"MemberType":"Event","Name":"ErrorDetailed","Parameters":[{"Name":"message","Type":{"Category":"Primitive","Name":"string"}},{"Name":"stackTrace","Type":{"Category":"Primitive","Name":"string"}},{"Name":"script","Type":{"Category":"Class","Name":"Instance"}},{"Name":"details","Type":{"Category":"Primitive","Name":"string"}},{"Name":"securityLevel","Type":{"Category":"Primitive","Name":"int"}}],"Security":"RobloxScriptSecurity","ThreadSafety":"Unsafe"}],"MemoryCategory":"Instances","Name":"ScriptContext","Superclass":"Instance","Tags":["NotCreatable","Service","NotReplicated"]},{"Members":[{"Category":"Data","MemberType":"Property","Name":"CurrentLine","Security":{"Read":"None","Write":"None"},"Serialization":{"CanLoad":false,"CanSave":false},"Tags":["ReadOnly","NotReplicated"],"ThreadSafety":"ReadSafe","ValueType":{"Category":"Primitive","Name":"int"}},{"Category":"Data","MemberType":"Property","Name":"IsDebugging","Security":{"Read":"None","Write":"None"},"Serialization":{"CanLoad":false,"CanSave":false},"Tags":["ReadOnly","NotReplicated"],"ThreadSafety":"ReadSafe","ValueType":{"Category":"Primitive","Name":"bool"}},{"Category":"Data","MemberType":"Property","Name":"IsPaused","Security":{"Read":"None","Write":"None"},"Serialization":{"CanLoad":false,"CanSave":false},"Tags":["ReadOnly","NotReplicated"],"ThreadSafety":"ReadSafe","ValueType":{"Category":"Primitive","Name":"bool"}},{"Category":"Data","MemberType":"Property","Name":"Script","Security":{"Read":"None","Write":"None"},"Serialization":{"CanLoad":false,"CanSave":false},"Tags":["ReadOnly","NotReplicated"],"ThreadSafety":"ReadSafe","ValueType":{"Category":"Class","Name":"Instance"}},{"MemberType":"Function","Name":"AddWatch","Parameters":[{"Name":"expression","Type":{"Category":"Primitive","Name":"string"}}],"ReturnType":{"Category":"Class","Name":"Instance"},"Security":"None","ThreadSafety":"Unsafe"},{"MemberType":"Function","Name":"GetBreakpoints","Parameters":[],"ReturnType":{"Category":"DataType","Name":"Objects"},"Security":"None","ThreadSafety":"Unsafe"},{"MemberType":"Function","Name":"GetGlobals","Parameters":[{"Default":"0","Name":"stackFrame","Type":{"Category":"Primitive","Name":"int"}}],"ReturnType":{"Category":"Group","Name":"Map"},"Security":"None","ThreadSafety":"Unsafe"},{"MemberType":"Function","Name":"GetLocals","Parameters":[{"Default":"0","Name":"stackFrame","Type":{"Category":"Primitive","Name":"int"}}],"ReturnType":{"Category":"Group","Name":"Map"},"Security":"None","ThreadSafety":"Unsafe"},{"MemberType":"Function","Name":"GetStack","Parameters":[],"ReturnType":{"Category":"Group","Name":"Array"},"Security":"None","ThreadSafety":"Unsafe"},{"MemberType":"Function","Name":"GetUpvalues","Parameters":[{"Default":"0","Name":"stackFrame","Type":{"Category":"Primitive","Name":"int"}}],"ReturnType":{"Category":"Group","Name":"Map"},"Security":"None","ThreadSafety":"Unsafe"},{"MemberType":"Function","Name":"GetWatchValue","Parameters":[{"Name":"watch","Type":{"Category":"Class","Name":"Instance"}}],"ReturnType":{"Category":"Group","Name":"Variant"},"Security":"None","ThreadSafety":"Unsafe"},{"MemberType":"Function","Name":"GetWatches","Parameters":[],"ReturnType":{"Category":"DataType","Name":"Objects"},"Security":"None","ThreadSafety":"Unsafe"},{"MemberType":"Function","Name":"SetBreakpoint","Parameters":[{"Name":"line","Type":{"Category":"Primitive","Name":"int"}},{"Name":"isContextDependentBreakpoint","Type":{"Category":"Primitive","Name":"bool"}}],"ReturnType":{"Category":"Class","Name":"Instance"},"Security":"None","ThreadSafety":"Unsafe"},{"MemberType":"Function","Name":"SetGlobal","Parameters":[{"Name":"name","Type":{"Category":"Primitive","Name":"string"}},{"Name":"value","Type":{"Category":"Group","Name":"Variant"}},{"Name":"stackFrame","Type":{"Category":"Primitive","Name":"int"}}],"ReturnType":{"Category":"Primitive","Name":"void"},"Security":"None","ThreadSafety":"Unsafe"},{"MemberType":"Function","Name":"SetLocal","Parameters":[{"Name":"name","Type":{"Category":"Primitive","Name":"string"}},{"Name":"value","Type":{"Category":"Group","Name":"Variant"}},{"Default":"0","Name":"stackFrame","Type":{"Category":"Primitive","Name":"int"}}],"ReturnType":{"Category":"Primitive","Name":"void"},"Security":"None","ThreadSafety":"Unsafe"},{"MemberType":"Function","Name":"SetUpvalue","Parameters":[{"Name":"name","Type":{"Category":"Primitive","Name":"string"}},{"Name":"value","Type":{"Category":"Group","Name":"Variant"}},{"Default":"0","Name":"stackFrame","Type":{"Category":"Primitive","Name":"int"}}],"ReturnType":{"Category":"Primitive","Name":"void"},"Security":"None","ThreadSafety":"Unsafe"},{"MemberType":"Event","Name":"BreakpointAdded","Parameters":[{"Name":"breakpoint","Type":{"Category":"Class","Name":"Instance"}}],"Security":"None","ThreadSafety":"Unsafe"},{"MemberType":"Event","Name":"BreakpointRemoved","Parameters":[{"Name":"breakpoint","Type":{"Category":"Class","Name":"Instance"}}],"Security":"None","ThreadSafety":"Unsafe"},{"MemberType":"Event","Name":"EncounteredBreak","Parameters":[{"Name":"line","Type":{"Category":"Primitive","Name":"int"}},{"Name":"breakReason","Type":{"Category":"Enum","Name":"BreakReason"}}],"Security":"None","ThreadSafety":"Unsafe"},{"MemberType":"Event","Name":"Resuming","Parameters":[],"Security":"None","ThreadSafety":"Unsafe"},{"MemberType":"Event","Name":"WatchAdded","Parameters":[{"Name":"watch","Type":{"Category":"Class","Name":"Instance"}}],"Security":"None","ThreadSafety":"Unsafe"},{"MemberType":"Event","Name":"WatchRemoved","Parameters":[{"Name":"watch","Type":{"Category":"Class","Name":"Instance"}}],"Security":"None","ThreadSafety":"Unsafe"}],"MemoryCategory":"Instances","Name":"ScriptDebugger","Superclass":"Instance","Tags":["NotCreatable"]},{"Members":[{"MemberType":"Function","Name":"GetInternalUri","Parameters":[],"ReturnType":{"Category":"Primitive","Name":"string"},"Security":"RobloxScriptSecurity","ThreadSafety":"Unsafe"},{"MemberType":"Function","Name":"GetLine","Parameters":[{"Default":"nil","Name":"lineIndex","Type":{"Category":"Primitive","Name":"int?"}}],"ReturnType":{"Category":"Primitive","Name":"string"},"Security":"PluginSecurity","ThreadSafety":"Unsafe"},{"MemberType":"Function","Name":"GetLineCount","Parameters":[],"ReturnType":{"Category":"Primitive","Name":"int"},"Security":"PluginSecurity","ThreadSafety":"Unsafe"},{"MemberType":"Function","Name":"GetScript","Parameters":[],"ReturnType":{"Category":"Class","Name":"LuaSourceContainer"},"Security":"PluginSecurity","ThreadSafety":"Unsafe"},{"MemberType":"Function","Name":"GetSelectedText","Parameters":[],"ReturnType":{"Category":"Primitive","Name":"string"},"Security":"PluginSecurity","ThreadSafety":"Unsafe"},{"MemberType":"Function","Name":"GetSelection","Parameters":[],"ReturnType":{"Category":"Group","Name":"Tuple"},"Security":"PluginSecurity","ThreadSafety":"Unsafe"},{"MemberType":"Function","Name":"GetSelectionEnd","Parameters":[],"ReturnType":{"Category":"Group","Name":"Tuple"},"Security":"PluginSecurity","ThreadSafety":"Unsafe"},{"MemberType":"Function","Name":"GetSelectionStart","Parameters":[],"ReturnType":{"Category":"Group","Name":"Tuple"},"Security":"PluginSecurity","ThreadSafety":"Unsafe"},{"MemberType":"Function","Name":"GetText","Parameters":[{"Default":"nil","Name":"startLine","Type":{"Category":"Primitive","Name":"int?"}},{"Default":"nil","Name":"startCharacter","Type":{"Category":"Primitive","Name":"int?"}},{"Default":"nil","Name":"endLine","Type":{"Category":"Primitive","Name":"int?"}},{"Default":"nil","Name":"endCharacter","Type":{"Category":"Primitive","Name":"int?"}}],"ReturnType":{"Category":"Primitive","Name":"string"},"Security":"PluginSecurity","ThreadSafety":"Unsafe"},{"MemberType":"Function","Name":"GetViewport","Parameters":[],"ReturnType":{"Category":"Group","Name":"Tuple"},"Security":"PluginSecurity","ThreadSafety":"Unsafe"},{"MemberType":"Function","Name":"HasSelectedText","Parameters":[],"ReturnType":{"Category":"Primitive","Name":"bool"},"Security":"PluginSecurity","ThreadSafety":"Unsafe"},{"MemberType":"Function","Name":"IsCommandBar","Parameters":[],"ReturnType":{"Category":"Primitive","Name":"bool"},"Security":"PluginSecurity","ThreadSafety":"Unsafe"},{"MemberType":"Function","Name":"CloseAsync","Parameters":[],"ReturnType":{"Category":"Group","Name":"Tuple"},"Security":"PluginSecurity","Tags":["Yields"],"ThreadSafety":"Unsafe"},{"MemberType":"Function","Name":"EditTextAsync","Parameters":[{"Name":"newText","Type":{"Category":"Primitive","Name":"string"}},{"Name":"startLine","Type":{"Category":"Primitive","Name":"int"}},{"Name":"startCharacter","Type":{"Category":"Primitive","Name":"int"}},{"Name":"endLine","Type":{"Category":"Primitive","Name":"int"}},{"Name":"endCharacter","Type":{"Category":"Primitive","Name":"int"}}],"ReturnType":{"Category":"Group","Name":"Tuple"},"Security":"PluginSecurity","Tags":["Yields"],"ThreadSafety":"Unsafe"},{"MemberType":"Function","Name":"ForceSetSelectionAsync","Parameters":[{"Name":"cursorLine","Type":{"Category":"Primitive","Name":"int"}},{"Name":"cursorCharacter","Type":{"Category":"Primitive","Name":"int"}},{"Default":"nil","Name":"anchorLine","Type":{"Category":"Primitive","Name":"int?"}},{"Default":"nil","Name":"anchorCharacter","Type":{"Category":"Primitive","Name":"int?"}}],"ReturnType":{"Category":"Group","Name":"Tuple"},"Security":"PluginSecurity","Tags":["Yields"],"ThreadSafety":"Unsafe"},{"MemberType":"Function","Name":"RequestSetSelectionAsync","Parameters":[{"Name":"cursorLine","Type":{"Category":"Primitive","Name":"int"}},{"Name":"cursorCharacter","Type":{"Category":"Primitive","Name":"int"}},{"Default":"nil","Name":"anchorLine","Type":{"Category":"Primitive","Name":"int?"}},{"Default":"nil","Name":"anchorCharacter","Type":{"Category":"Primitive","Name":"int?"}}],"ReturnType":{"Category":"Group","Name":"Tuple"},"Security":"PluginSecurity","Tags":["Yields"],"ThreadSafety":"Unsafe"},{"MemberType":"Event","Name":"SelectionChanged","Parameters":[{"Name":"positionLine","Type":{"Category":"Primitive","Name":"int64"}},{"Name":"positionCharacter","Type":{"Category":"Primitive","Name":"int64"}},{"Name":"anchorLine","Type":{"Category":"Primitive","Name":"int64"}},{"Name":"anchorCharacter","Type":{"Category":"Primitive","Name":"int64"}}],"Security":"PluginSecurity","ThreadSafety":"Unsafe"},{"MemberType":"Event","Name":"ViewportChanged","Parameters":[{"Name":"startLine","Type":{"Category":"Primitive","Name":"int64"}},{"Name":"endLine","Type":{"Category":"Primitive","Name":"int64"}}],"Security":"PluginSecurity","ThreadSafety":"Unsafe"}],"MemoryCategory":"Instances","Name":"ScriptDocument","Superclass":"Instance","Tags":["NotCreatable","NotReplicated"]},{"Members":[{"MemberType":"Function","Name":"DeregisterAutocompleteCallback","Parameters":[{"Name":"name","Type":{"Category":"Primitive","Name":"string"}}],"ReturnType":{"Category":"Primitive","Name":"void"},"Security":"PluginSecurity","ThreadSafety":"Unsafe"},{"MemberType":"Function","Name":"FindScriptDocument","Parameters":[{"Name":"script","Type":{"Category":"Class","Name":"LuaSourceContainer"}}],"ReturnType":{"Category":"Class","Name":"ScriptDocument"},"Security":"PluginSecurity","ThreadSafety":"Unsafe"},{"MemberType":"Function","Name":"GetScriptDocuments","Parameters":[],"ReturnType":{"Category":"DataType","Name":"Objects"},"Security":"PluginSecurity","ThreadSafety":"Unsafe"},{"MemberType":"Function","Name":"RegisterAutocompleteCallback","Parameters":[{"Name":"name","Type":{"Category":"Primitive","Name":"string"}},{"Name":"priority","Type":{"Category":"Primitive","Name":"int"}},{"Name":"callbackFunction","Type":{"Category":"DataType","Name":"Function"}}],"ReturnType":{"Category":"Primitive","Name":"void"},"Security":"PluginSecurity","ThreadSafety":"Unsafe"},{"MemberType":"Function","Name":"OpenScriptDocumentAsync","Parameters":[{"Name":"script","Type":{"Category":"Class","Name":"LuaSourceContainer"}}],"ReturnType":{"Category":"Group","Name":"Tuple"},"Security":"PluginSecurity","Tags":["Yields"],"ThreadSafety":"Unsafe"},{"MemberType":"Event","Name":"TextDocumentDidChange","Parameters":[{"Name":"document","Type":{"Category":"Class","Name":"ScriptDocument"}},{"Name":"changesArray","Type":{"Category":"Group","Name":"Variant"}}],"Security":"PluginSecurity","ThreadSafety":"Unsafe"},{"MemberType":"Event","Name":"TextDocumentDidClose","Parameters":[{"Name":"oldDocument","Type":{"Category":"Class","Name":"ScriptDocument"}}],"Security":"PluginSecurity","ThreadSafety":"Unsafe"},{"MemberType":"Event","Name":"TextDocumentDidOpen","Parameters":[{"Name":"newDocument","Type":{"Category":"Class","Name":"ScriptDocument"}}],"Security":"PluginSecurity","ThreadSafety":"Unsafe"}],"MemoryCategory":"Instances","Name":"ScriptEditorService","Superclass":"Instance","Tags":["NotCreatable","Service","NotReplicated"]},{"Members":[{"MemberType":"Function","Name":"GetSourceContainerByScriptGuid","Parameters":[{"Name":"guid","Type":{"Category":"Primitive","Name":"string"}}],"ReturnType":{"Category":"Class","Name":"LuaSourceContainer"},"Security":"RobloxScriptSecurity","ThreadSafety":"Unsafe"}],"MemoryCategory":"Instances","Name":"ScriptRegistrationService","Superclass":"Instance","Tags":["NotCreatable","Service","NotReplicated"]},{"Members":[],"MemoryCategory":"Instances","Name":"ScriptService","Superclass":"Instance","Tags":["NotCreatable","Service"]},{"Members":[{"Category":"Data","MemberType":"Property","Name":"ActiveInstance","Security":{"Read":"RobloxScriptSecurity","Write":"RobloxScriptSecurity"},"Serialization":{"CanLoad":false,"CanSave":false},"Tags":["Hidden","ReadOnly","NotReplicated"],"ThreadSafety":"ReadSafe","ValueType":{"Category":"Class","Name":"Instance"}},{"Category":"Appearance","MemberType":"Property","Name":"SelectionLineThickness","Security":{"Read":"None","Write":"None"},"Serialization":{"CanLoad":false,"CanSave":true},"Tags":["Hidden","ReadOnly","NotReplicated"],"ThreadSafety":"ReadSafe","ValueType":{"Category":"Primitive","Name":"int"}},{"Category":"Appearance","MemberType":"Property","Name":"SelectionThickness","Security":{"Read":"None","Write":"None"},"Serialization":{"CanLoad":false,"CanSave":false},"Tags":["ReadOnly","NotReplicated"],"ThreadSafety":"ReadSafe","ValueType":{"Category":"Primitive","Name":"float"}},{"MemberType":"Function","Name":"Add","Parameters":[{"Name":"instancesToAdd","Type":{"Category":"DataType","Name":"Objects"}}],"ReturnType":{"Category":"Primitive","Name":"void"},"Security":"PluginSecurity","ThreadSafety":"Unsafe"},{"MemberType":"Function","Name":"ClearTerrainSelectionHack","Parameters":[],"ReturnType":{"Category":"Primitive","Name":"void"},"Security":"RobloxScriptSecurity","ThreadSafety":"Unsafe"},{"MemberType":"Function","Name":"Get","Parameters":[],"ReturnType":{"Category":"DataType","Name":"Objects"},"Security":"PluginSecurity","ThreadSafety":"Unsafe"},{"MemberType":"Function","Name":"Remove","Parameters":[{"Name":"instancesToRemove","Type":{"Category":"DataType","Name":"Objects"}}],"ReturnType":{"Category":"Primitive","Name":"void"},"Security":"PluginSecurity","ThreadSafety":"Unsafe"},{"MemberType":"Function","Name":"Set","Parameters":[{"Name":"selection","Type":{"Category":"DataType","Name":"Objects"}}],"ReturnType":{"Category":"Primitive","Name":"void"},"Security":"PluginSecurity","ThreadSafety":"Unsafe"},{"MemberType":"Function","Name":"SetTerrainSelectionHack","Parameters":[{"Name":"center","Type":{"Category":"DataType","Name":"Vector3"}},{"Name":"size","Type":{"Category":"DataType","Name":"Vector3"}}],"ReturnType":{"Category":"Primitive","Name":"void"},"Security":"RobloxScriptSecurity","ThreadSafety":"Unsafe"},{"MemberType":"Event","Name":"SelectionChanged","Parameters":[],"Security":"None","ThreadSafety":"Unsafe"}],"MemoryCategory":"Instances","Name":"Selection","Superclass":"Instance","Tags":["NotCreatable","Service"]},{"Members":[{"Category":"Behavior","MemberType":"Property","Name":"LoadStringEnabled","Security":{"Read":"None","Write":"None"},"Serialization":{"CanLoad":true,"CanSave":true},"Tags":["NotReplicated","NotScriptable"],"ThreadSafety":"ReadSafe","ValueType":{"Category":"Primitive","Name":"bool"}}],"MemoryCategory":"Instances","Name":"ServerScriptService","Superclass":"Instance","Tags":["NotCreatable","Service","NotReplicated"]},{"Members":[],"MemoryCategory":"Instances","Name":"ServerStorage","Superclass":"Instance","Tags":["NotCreatable","Service","NotReplicated"]},{"Members":[{"MemberType":"Function","Name":"FindService","Parameters":[{"Name":"className","Type":{"Category":"Primitive","Name":"string"}}],"ReturnType":{"Category":"Class","Name":"Instance"},"Security":"None","ThreadSafety":"Safe"},{"MemberType":"Function","Name":"GetService","Parameters":[{"Name":"className","Type":{"Category":"Primitive","Name":"string"}}],"ReturnType":{"Category":"Class","Name":"Instance"},"Security":"None","ThreadSafety":"Unsafe"},{"MemberType":"Function","Name":"getService","Parameters":[{"Name":"className","Type":{"Category":"Primitive","Name":"string"}}],"ReturnType":{"Category":"Class","Name":"Instance"},"Security":"None","Tags":["Deprecated"],"ThreadSafety":"Unsafe"},{"MemberType":"Function","Name":"service","Parameters":[{"Name":"className","Type":{"Category":"Primitive","Name":"string"}}],"ReturnType":{"Category":"Class","Name":"Instance"},"Security":"None","Tags":["Deprecated"],"ThreadSafety":"Unsafe"},{"MemberType":"Event","Name":"Close","Parameters":[],"Security":"None","ThreadSafety":"Unsafe"},{"MemberType":"Event","Name":"CloseLate","Parameters":[],"Security":"LocalUserSecurity","ThreadSafety":"Unsafe"},{"MemberType":"Event","Name":"ServiceAdded","Parameters":[{"Name":"service","Type":{"Category":"Class","Name":"Instance"}}],"Security":"None","ThreadSafety":"Unsafe"},{"MemberType":"Event","Name":"ServiceRemoving","Parameters":[{"Name":"service","Type":{"Category":"Class","Name":"Instance"}}],"Security":"None","ThreadSafety":"Unsafe"}],"MemoryCategory":"Instances","Name":"ServiceProvider","Superclass":"Instance","Tags":["NotCreatable","NotBrowsable"]}]}